Workbook
Name Slicer_Store_Name_Region: #N/A

Sheet Customer_Dim
A1: Customer_ID | B1: Name | C1: Age | D1: Gender | E1: City | F1: State | G1: Country | H1: Loyalty_Level
A2: CUST1000 | B2: Sheena Bonilla | C2: 55 | D2: Male | E2: Donaldton | F2: North Carolina | G2: USA | H2: Unknown
A3: CUST1001 | B3: Eugene Nelson | C3: 26 | D3: Female | E3: Phillipsmouth | F3: North Dakota | G3: USA | H3: Platinum | J3: Highlight Cell Rules:Above 30 years of age is highlighted using highlight cell rules.
A4: CUST1002 | B4: Dr. Benjamin Price | C4: 29 | D4: Female | E4: Kylebury | F4: Alabama | G4: USA | H4: Platinum
A5: CUST1003 | B5: Jeremy Harris | C5: 59 | D5: Female | E5: Thomastown | F5: Ohio | G5: USA | H5: Bronze
A6: CUST1004 | B6: Caroline Collins | C6: 64 | D6: Female | E6: Nicholasshire | F6: California | G6: USA | H6: Silver
A7: CUST1005 | B7: Christine Vaughn | C7: 24 | D7: Male | E7: East Amandamouth | F7: Oregon | G7: USA | H7: Bronze
A8: CUST1006 | B8: Amber Jackson | C8: 29 | D8: Female | E8: Deborahborough | F8: South Dakota | G8: USA | H8: Platinum
A9: CUST1007 | B9: Daniel Boyd | C9: 29 | D9: Female | E9: West Pamelafurt | F9: West Virginia | G9: USA | H9: Bronze
A10: CUST1008 | B10: Melissa Howard | C10: 53 | D10: Female | E10: Maynardton | F10: New Hampshire | G10: USA | H10: Gold
A11: CUST1009 | B11: Ms. Maria Leach | C11: 64 | D11: Male | E11: Melissashire | F11: Pennsylvania | G11: USA | H11: Platinum
A12: CUST1010 | B12: Dominic Page | C12: 53 | D12: Male | E12: Port Michaelburgh | F12: Pennsylvania | G12: USA | H12: Bronze
A13: CUST1011 | B13: Brian Lopez | C13: 28 | D13: Female | E13: East Krista | F13: New York | G13: USA | H13: Gold
A14: CUST1012 | B14: Kenneth Lambert | C14: 55 | D14: Female | E14: North Kathryn | F14: Kansas | G14: USA | H14: Platinum
A15: CUST1013 | B15: Nathan Hernandez | C15: 32 | D15: Female | E15: New Becky | F15: Montana | G15: USA | H15: Silver
... A501: CUST1499 | B501: Philip Pennington | C501: 27 | D501: Female | E501: East Valerieview | F501: Oregon | G501: USA | H501: Platinum

Sheet Product_Dim
A1: Product_ID | B1: Product Name with category | C1: Sub_Category | D1: Brand | E1: Cost | F1: Stock range | G1: Stock Value
A2: PROD0 | B2: Brother Laser Printer-Electronics | C2: Computer | D2: Hunt Inc | E2: 112.42 | F2: =IF(Table2[[#This Row],[Stock Value]]>200,"High","Low") -> High | G2: 416
A3: PROD1 | B3: Men's Graphic T-Shirt-Clothing | C3: Tops | D3: Terry-Moore | E3: 342.56 | F3: =IF(Table2[[#This Row],[Stock Value]]>200,"High","Low") -> Low | G3: 181 | I3: IF function:
A4: PROD2 | B4: Women's Casual Hoodie-Clothing | C4: Outerwear | D4: Sims Inc | E4: 254.62087 | F4: =IF(Table2[[#This Row],[Stock Value]]>200,"High","Low") -> High | G4: 352 | I4: IF(G2>200,"High","Low")
A5: PROD3 | B5: Men's Running Jacket-Clothing | C5: Outerwear | D5: Pineda Ltd | E5: 364.67 | F5: =IF(Table2[[#This Row],[Stock Value]]>200,"High","Low") -> High | G5: 452 | I5: Color bars are applied based on the price range.
A6: PROD4 | B6: Women's Yoga Pants-Clothing | C6: Bottoms | D6: Gonzales-Davis | E6: 306.46 | F6: =IF(Table2[[#This Row],[Stock Value]]>200,"High","Low") -> High | G6: 487 | I6: SUMIF Function: | K6: Cost in accessories sub category is added.
A7: PROD5 | B7: Men's Leather Belt-Clothing | C7: Accessories | D7: Baldwin, Garza and Gonzalez | E7: 261 | F7: =IF(Table2[[#This Row],[Stock Value]]>200,"High","Low") -> Low | G7: 59 | I7: Formula used: | K7: SUMIF(C2:C101,C7,E2:E101)
A8: PROD6 | B8: Herbal Face Moisturizer-Beauty | C8: Skincare | D8: Davidson PLC | E8: 312.8 | F8: =IF(Table2[[#This Row],[Stock Value]]>200,"High","Low") -> High | G8: 350 | I8: =SUMIF(C2:C101,C13,E2:E101) -> 3708.07
A9: PROD7 | B9: LED Table Lamp-Home | C9: Lighting | D9: Harrell LLC | E9: 218.86 | F9: =IF(Table2[[#This Row],[Stock Value]]>200,"High","Low") -> Low | G9: 170
A10: PROD8 | B10: Wireless Bluetooth Earbuds-Electronics | C10: Audio | D10: Perez-Johnston | E10: 439.07 | F10: =IF(Table2[[#This Row],[Stock Value]]>200,"High","Low") -> Low | G10: 142
A11: PROD9 | B11: Adjustable Dumbbell Set-Sports | C11: Fitness | D11: Hill PLC | E11: 495.72 | F11: =IF(Table2[[#This Row],[Stock Value]]>200,"High","Low") -> High | G11: 323
A12: PROD10 | B12: Ceramic Kitchen Bowl Set-Home | C12: Kitchen | D12: Hamilton Group | E12: 298.86 | F12: =IF(Table2[[#This Row],[Stock Value]]>200,"High","Low") -> High | G12: 308
A13: PROD11 | B13: HD Smart TV Stick-Electronics | C13: Accessories | D13: Gibson, Hobbs and Weaver | E13: 449.4 | F13: =IF(Table2[[#This Row],[Stock Value]]>200,"High","Low") -> High | G13: 270.80233
A14: PROD12 | B14: Hair Strengthening Shampoo-Beauty | C14: Haircare | D14: Rice LLC | E14: 115.82 | F14: =IF(Table2[[#This Row],[Stock Value]]>200,"High","Low") -> High | G14: 460
A15: PROD13 | B15: USB-C Fast Charger-Electronics | C15: Accessories | D15: Dawson-Perkins | E15: 242.23 | F15: =IF(Table2[[#This Row],[Stock Value]]>200,"High","Low") -> High | G15: 453
A16: PROD14 | B16: Decorative Wall Mirror-Home | C16: Decor | D16: Luna, Anderson and Bowman | E16: 48.01 | F16: =IF(Table2[[#This Row],[Stock Value]]>200,"High","Low") -> High | G16: 439
A17: PROD15 | B17: 4K Home Projector-Electronics | C17: Appliances | D17: Thomas LLC | E17: 465.34 | F17: =IF(Table2[[#This Row],[Stock Value]]>200,"High","Low") -> High | G17: 301
A18: PROD16 | B18: Beard Grooming Kit-Beauty | C18: Grooming | D18: Erickson-Green | E18: 337.42 | F18: =IF(Table2[[#This Row],[Stock Value]]>200,"High","Low") -> High | G18: 256
A19: PROD17 | B19: Soccer Training Cone Set-Sports | C19: Accessories | D19: Ford, Murphy and Wilson | E19: 144.53 | F19: =IF(Table2[[#This Row],[Stock Value]]>200,"High","Low") -> High | G19: 367
A20: PROD18 | B20: Women's Denim Jeans-Clothing | C20: Bottoms | D20: Guerra-Hendrix | E20: 245.77831 | F20: =IF(Table2[[#This Row],[Stock Value]]>200,"High","Low") -> High | G20: 343
... A101: PROD99 | B101: Stainless Steel Cookware Set-Home | C101: Kitchen | D101: Campbell Ltd | E101: 201.41 | F101: =IF(Table2[[#This Row],[Stock Value]]>200,"High","Low") -> Low | G101: 146

Sheet Store_Dim
A1: Column1 | B1: Column12 | C1: Column5 | D1: Column6
A2: Store_ID | B2: Store_Name-Region | C2: City | D2: Store_Type
A3: STORE0 | B3: Rivera-Warner-East | C3: Washingtonfurt | D3: Flagship
A4: STORE1 | B4: Martinez, Adkins and Johnson-North | C4: Danielmouth | D4: Flagship
A5: STORE2 | B5: Black-Horn-South | C5: North Nancyview | D5: Outlet
A6: STORE3 | B6: Johnson-Wright-North | C6: Hoodberg | D6: Outlet
A7: STORE4 | B7: Alexander Group-South | C7: Port Sharon | D7: Online
A8: STORE5 | B8: Gray Ltd-North | C8: New Michaelchester | D8: Outlet
A9: STORE6 | B9: Benson-Elliott-East | C9: Port Josephberg | D9: Online
A10: STORE7 | B10: Martinez-Mullins-South | C10: Williamsfurt | D10: Online
A11: STORE8 | B11: Bean, Jones and Park-West | C11: Thompsonborough | D11: Online
A12: STORE9 | B12: Moore, Padilla and Butler-South | C12: East Johnstad | D12: Flagship
... A22: STORE19 | B22: Mann-Austin-East | C22: Vasquezborough | D22: Online

Sheet Region -yearwise
A3: Sum of Total_amount | B3: Column Labels
A4: Row Labels | B4: Aguirre-Keller-South | C4: Alexander Group-South | D4: Bean, Jones and Park-West | E4: Benson-Elliott-East | F4: Black-Horn-South | G4: Frederick-Wright-West | H4: Gardner, Humphrey and Contreras-East | I4: Gray Ltd-North | J4: Guerrero-Schmitt-East | K4: Holloway Ltd-North | L4: Mcdonald Inc-South | M4: Moore, Padilla and Butler-South | N4: Rivera-Warner-East | O4: Shelton PLC-North | P4: Thomas, Bridges and Harris-North | Q4: Grand Total
A5: 2023 | B5: 4958.7861 | C5: 12055.56 | D5: 15838.583 | E5: 17550.365 | F5: 14092.537 | G5: 2266.0419 | H5: 10046.363 | I5: 10700.706 | J5: 10834.37 | K5: 12814.569 | L5: 5524.3127 | M5: 3793.6722 | N5: 9046.0773 | O5: 12964.754 | P5: 8439.0101 | Q5: 150925.71
A6: 2024 | B6: 54325.894 | C6: 63483.123 | D6: 64837.021 | E6: 49290.706 | F6: 46410.977 | G6: 66040.747 | H6: 52349.374 | I6: 42798.136 | J6: 46461.761 | K6: 67829.833 | L6: 57066.414 | M6: 63351.601 | N6: 33962.257 | O6: 54110.989 | P6: 62045.402 | Q6: 824364.24
A7: 2025 | B7: 33763.46 | C7: 43275.432 | D7: 78295.859 | E7: 47692.726 | F7: 38457.294 | G7: 43398.155 | H7: 52005.734 | I7: 28733.507 | J7: 47016.923 | K7: 41887.31 | L7: 43657.557 | M7: 42957.125 | N7: 42130.221 | O7: 32603.344 | P7: 46344.808 | Q7: 662219.46
A8: Grand Total | B8: 93048.141 | C8: 118814.12 | D8: 158971.46 | E8: 114533.8 | F8: 98960.808 | G8: 111704.94 | H8: 114401.47 | I8: 82232.348 | J8: 104313.05 | K8: 122531.71 | L8: 106248.28 | M8: 110102.4 | N8: 85138.555 | O8: 99679.086 | P8: 116829.22 | Q8: 1637509.4

Sheet Monthwise
A3: Sum of Total_amount | B3: Column Labels
A4: Row Labels | B4: 2023 | C4: 2024 | D4: 2025 | E4: Grand Total
A5: April | C5: 4889.3898 | D5: 6057.9152 | E5: 10947.305
A6: August | C6: 3410.4235 | D6: 1511.3323 | E6: 4921.7558
A7: December | B7: 1139.2544 | C7: 5384.6058 | E7: 6523.8602
A8: February | C8: 3561.8304 | D8: 1034.7036 | E8: 4596.534
A9: January | C9: 3271.7152 | D9: 10234.723 | E9: 13506.438
A10: July | C10: 4931.665 | D10: 3308.796 | E10: 8240.461
A11: June | C11: 3819.8173 | E11: 3819.8173
A12: March | C12: 2691.3326 | D12: 4921.7572 | E12: 7613.0898
A13: May | C13: 4006.7943 | D13: 4045.018 | E13: 8051.8123
A14: November | B14: 2638.8927 | C14: 5205.7253 | E14: 7844.618
A15: October | B15: 1180.639 | C15: 5455.2694 | D15: 2017.5012 | E15: 8653.4096
A16: September | C16: 7697.3256 | D16: 631.7138 | E16: 8329.0394
A17: Grand Total | B17: 4958.7861 | C17: 54325.894 | D17: 33763.46 | E17: 93048.141
F21: Total amount is calculated for different months with respective year.Slicers is applied for Aguirre-keller-south region and | K21: column chart is applied for analysis.
G22: X-axis-Month
G23: Y-axis-Total Amount

Sheet Category Wise
A3: Row Labels | B3: Sum of Total_amount
A4: Makeup Brush Set-Beauty | B4: 7948.3905
A5: Vitamin C Face Serum-Beauty | B5: 9681.9319
A6: Herbal Face Moisturizer-Beauty | B6: 9937.0898 | D6: Total Amount for different categories is calculated for this dataset.
A7: Gaming Mouse Pad XL-Electronics | B7: 12127.249
A8: Sports Stopwatch Basic-Sports | B8: 12301.164
A9: Fabric Sofa Throw Blanket-Home | B9: 12665.901
A10: Men's Formal Shirt-Clothing | B10: 12949.499
A11: Adjustable Dumbbell Set-Sports | B11: 13115.581
A12: Rugby Ball-Sports | B12: 13834.392
A13: Stainless Steel Cutlery Set-Home | B13: 14029.913
A14: Adjustable Jump Rope-Sports | B14: 14177.224
A15: Men's Track Pants-Clothing | B15: 14300.937
A16: Women's Denim Jeans-Clothing | B16: 15084.944
A17: Sports Stopwatch Timer-Sports | B17: 15145.865
A18: Women's Summer Dress-Clothing | B18: 15635.99
... A104: Grand Total | B104: 2175265

Sheet Region Wise
A3: Row Labels | B3: Sum of Total_amount | C3: Count of Quantity
A4: Aguirre-Keller-South | B4: 93048.141 | C4: 88
A5: Alexander Group-South | B5: 118814.12 | C5: 102
A6: Bean, Jones and Park-West | B6: 158971.46 | C6: 127
A7: Benson-Elliott-East | B7: 114533.8 | C7: 106
A8: Black-Horn-South | B8: 98960.808 | C8: 92
A9: Frederick-Wright-West | B9: 111704.94 | C9: 106
A10: Gardner, Humphrey and Contreras-East | B10: 114401.47 | C10: 95
A11: Gray Ltd-North | B11: 82232.348 | C11: 83
A12: Guerrero-Schmitt-East | B12: 104313.05 | C12: 105
A13: Hill, Wagner and Ballard-East | B13: 109454.57 | C13: 97
A14: Holloway Ltd-North | B14: 122531.71 | C14: 110
A15: Johnson-Wright-North | B15: 125011.83 | C15: 114
... A20: Moore, Padilla and Butler-South | B20: 110102.4 | C20: 96
A21: Rivera-Warner-East | B21: 85138.555 | C21: 93 | F21: Regionwise sales for different regions is calculated using Line chart
A22: Shelton PLC-North | B22: 99679.086 | C22: 95 | F22: X-axis-Sum of total amount,count of quantity
A23: Thomas, Bridges and Harris-North | B23: 116829.22 | C23: 100 | F23: Y-axis-Store name-region
A24: Grand Total | B24: 2175265 | C24: 2000

Sheet payment mode
A3: Sum of Total_amount | B3: Column Labels
A4: Row Labels | B4: 2023 | C4: 2024 | D4: 2025 | E4: Grand Total
A5: COD | B5: 67845.315 | C5: 358305.66 | D5: 277552.36 | E5: 703703.34
A6: Credit Card | B6: 84467.031 | C6: 319429.08 | D6: 310947.46 | E6: 714843.57
A7: PayPal | B7: 71855.543 | C7: 416140.58 | D7: 268721.98 | E7: 756718.1
A8: Grand Total | B8: 224167.89 | C8: 1093875.3 | D8: 857221.8 | E8: 2175265
A12: Pie chart is created for payment type with respective sum of total amount
A13: From this chart,most of payment done with credit card type.

Sheet Quarter Wise
A3: Row Labels | B3: Sum of Total_amount
A4: Q1 | B4: 540227.6
A5: Q2 | B5: 502016.01
A6: Q3 | B6: 575956.87
A7: Q4 | B7: 557064.52
A8: Grand Total | B8: 2175265
A10: Sum of total amount is calculated for different quarters.From this Quarter-4 has higher amount of sales.

Sheet Sales_Fact
A1: Sales_ID | B1: Quarter | C1: Month | D1: Year | E1: Order_Date | F1: Customer Name | G1: Customer City | H1: Customer_ID | I1: Product name with category | J1: Product_ID | K1: Store_Name-Region | L1: Store_ID | M1: Quantity | N1: Unit_Price | O1: Discount | P1: Payment_Type | Q1: Total_amount
A2: SALE0 | B2: ="Q" &ROUNDUP(MONTH(E2)/3,0) -> Q3 | C2: =TEXT(Table1[[#This Row],[Order_Date]],"mmmm") -> July | D2: =YEAR(Table1[[#This Row],[Order_Date]]) -> 2024 | E2: 45480 | F2: =VLOOKUP(Table1[[#This Row],[Customer_ID]],Customer_Dim!$A$2:$H$501,2,FALSE) -> Sarah Smith | G2: =_xlfn.XLOOKUP(Table1[[#This Row],[Customer_ID]],Customer_Dim!$A$2:$A$501,Customer_Dim!$E$2:$E$501) -> Kathleenport | H2: CUST1409 | I2: =VLOOKUP(Table1[[#This Row],[Product_ID]],Product_Dim!$A$2:$G$101,2,FALSE) -> Cricket Bat-Sports | J2: PROD97 | K2: =VLOOKUP(Table1[[#This Row],[Store_ID]],Store_Dim!$A$3:$D$22,2,FALSE) -> Johnson-Wright-North | L2: STORE3 | M2: 1 | N2: 218.04 | O2: 0.09 | P2: Credit Card | Q2: 198.4164
A3: SALE1 | B3: ="Q" &ROUNDUP(MONTH(E3)/3,0) -> Q4 | C3: =TEXT(Table1[[#This Row],[Order_Date]],"mmmm") -> December | D3: =YEAR(Table1[[#This Row],[Order_Date]]) -> 2023 | E3: 45285 | F3: =VLOOKUP(Table1[[#This Row],[Customer_ID]],Customer_Dim!$A$2:$H$501,2,FALSE) -> Michael Foley | G3: =_xlfn.XLOOKUP(Table1[[#This Row],[Customer_ID]],Customer_Dim!$A$2:$A$501,Customer_Dim!$E$2:$E$501) -> Oneillfurt | H3: CUST1467 | I3: =VLOOKUP(Table1[[#This Row],[Product_ID]],Product_Dim!$A$2:$G$101,2,FALSE) -> Bluetooth Car Audio System-Electronics | J3: PROD74 | K3: =VLOOKUP(Table1[[#This Row],[Store_ID]],Store_Dim!$A$3:$D$22,2,FALSE) -> Holloway Ltd-North | L3: STORE17 | M3: 1 | N3: 104.47 | O3: 0.27 | P3: PayPal | Q3: 228.7893 | V3: Sum | W3: =SUM(Q2:Q2001) -> 2175265
A4: SALE2 | B4: ="Q" &ROUNDUP(MONTH(E4)/3,0) -> Q2 | C4: =TEXT(Table1[[#This Row],[Order_Date]],"mmmm") -> June | D4: =YEAR(Table1[[#This Row],[Order_Date]]) -> 2024 | E4: 45446 | F4: =VLOOKUP(Table1[[#This Row],[Customer_ID]],Customer_Dim!$A$2:$H$501,2,FALSE) -> Christopher Sutton | G4: =_xlfn.XLOOKUP(Table1[[#This Row],[Customer_ID]],Customer_Dim!$A$2:$A$501,Customer_Dim!$E$2:$E$501) -> Deborahberg | H4: CUST1056 | I4: =VLOOKUP(Table1[[#This Row],[Product_ID]],Product_Dim!$A$2:$G$101,2,FALSE) -> Men's Roll-On Perfume-Beauty | J4: PROD49 | K4: =VLOOKUP(Table1[[#This Row],[Store_ID]],Store_Dim!$A$3:$D$22,2,FALSE) -> Bean, Jones and Park-West | L4: STORE8 | M4: 1 | N4: 914.05 | O4: 0.25 | P4: Credit Card | Q4: 2742.15 | V4: Average | W4: =W3/2000 -> 1087.6325
A5: SALE3 | B5: ="Q" &ROUNDUP(MONTH(E5)/3,0) -> Q4 | C5: =TEXT(Table1[[#This Row],[Order_Date]],"mmmm") -> November | D5: =YEAR(Table1[[#This Row],[Order_Date]]) -> 2023 | E5: 45259 | F5: =VLOOKUP(Table1[[#This Row],[Customer_ID]],Customer_Dim!$A$2:$H$501,2,FALSE) -> John Jordan | G5: =_xlfn.XLOOKUP(Table1[[#This Row],[Customer_ID]],Customer_Dim!$A$2:$A$501,Customer_Dim!$E$2:$E$501) -> Port Crystalberg | H5: CUST1346 | I5: =VLOOKUP(Table1[[#This Row],[Product_ID]],Product_Dim!$A$2:$G$101,2,FALSE) -> Wireless Mouse-Electronics | J5: PROD76 | K5: =VLOOKUP(Table1[[#This Row],[Store_ID]],Store_Dim!$A$3:$D$22,2,FALSE) -> Bean, Jones and Park-West | L5: STORE8 | M5: 1 | N5: 921.51 | O5: 0.16 | P5: COD | Q5: 774.0684
A6: SALE4 | B6: ="Q" &ROUNDUP(MONTH(E6)/3,0) -> Q1 | C6: =TEXT(Table1[[#This Row],[Order_Date]],"mmmm") -> January | D6: =YEAR(Table1[[#This Row],[Order_Date]]) -> 2024 | E6: 45297 | F6: =VLOOKUP(Table1[[#This Row],[Customer_ID]],Customer_Dim!$A$2:$H$501,2,FALSE) -> Amanda Powell | G6: =_xlfn.XLOOKUP(Table1[[#This Row],[Customer_ID]],Customer_Dim!$A$2:$A$501,Customer_Dim!$E$2:$E$501) -> South William | H6: CUST1493 | I6: =VLOOKUP(Table1[[#This Row],[Product_ID]],Product_Dim!$A$2:$G$101,2,FALSE) -> Men's Hair Styling Gel-Beauty | J6: PROD59 | K6: =VLOOKUP(Table1[[#This Row],[Store_ID]],Store_Dim!$A$3:$D$22,2,FALSE) -> Gray Ltd-North | L6: STORE5 | M6: 1 | N6: 745.3 | O6: 0.18 | P6: Credit Card | Q6: 1833.438 | V6: Analysis Toolpak
A7: SALE5 | B7: ="Q" &ROUNDUP(MONTH(E7)/3,0) -> Q3 | C7: =TEXT(Table1[[#This Row],[Order_Date]],"mmmm") -> July | D7: =YEAR(Table1[[#This Row],[Order_Date]]) -> 2024 | E7: 45499 | F7: =VLOOKUP(Table1[[#This Row],[Customer_ID]],Customer_Dim!$A$2:$H$501,2,FALSE) -> Anthony Phillips | G7: =_xlfn.XLOOKUP(Table1[[#This Row],[Customer_ID]],Customer_Dim!$A$2:$A$501,Customer_Dim!$E$2:$E$501) -> North Davidport | H7: CUST1116 | I7: =VLOOKUP(Table1[[#This Row],[Product_ID]],Product_Dim!$A$2:$G$101,2,FALSE) -> 4K Home Projector-Electronics | J7: PROD15 | K7: =VLOOKUP(Table1[[#This Row],[Store_ID]],Store_Dim!$A$3:$D$22,2,FALSE) -> Martinez-Mullins-South | L7: STORE7 | M7: 1 | N7: 147.01 | O7: 0.19 | P7: COD | Q7: 357.2343
A8: SALE6 | B8: ="Q" &ROUNDUP(MONTH(E8)/3,0) -> Q3 | C8: =TEXT(Table1[[#This Row],[Order_Date]],"mmmm") -> July | D8: =YEAR(Table1[[#This Row],[Order_Date]]) -> 2025 | E8: 45850 | F8: =VLOOKUP(Table1[[#This Row],[Customer_ID]],Customer_Dim!$A$2:$H$501,2,FALSE) -> John Scott | G8: =_xlfn.XLOOKUP(Table1[[#This Row],[Customer_ID]],Customer_Dim!$A$2:$A$501,Customer_Dim!$E$2:$E$501) -> South Christopher | H8: CUST1016 | I8: =VLOOKUP(Table1[[#This Row],[Product_ID]],Product_Dim!$A$2:$G$101,2,FALSE) -> Premium Blanket Throw-Home | J8: PROD56 | K8: =VLOOKUP(Table1[[#This Row],[Store_ID]],Store_Dim!$A$3:$D$22,2,FALSE) -> Alexander Group-South | L8: STORE4 | M8: 1 | N8: 785.31 | O8: 0.15 | P8: PayPal | Q8: 1335.027 | W8: Mean | X8: 1088.0773
A9: SALE7 | B9: ="Q" &ROUNDUP(MONTH(E9)/3,0) -> Q4 | C9: =TEXT(Table1[[#This Row],[Order_Date]],"mmmm") -> November | D9: =YEAR(Table1[[#This Row],[Order_Date]]) -> 2023 | E9: 45248 | F9: =VLOOKUP(Table1[[#This Row],[Customer_ID]],Customer_Dim!$A$2:$H$501,2,FALSE) -> Patrick Roberts | G9: =_xlfn.XLOOKUP(Table1[[#This Row],[Customer_ID]],Customer_Dim!$A$2:$A$501,Customer_Dim!$E$2:$E$501) -> Jaredville | H9: CUST1152 | I9: =VLOOKUP(Table1[[#This Row],[Product_ID]],Product_Dim!$A$2:$G$101,2,FALSE) -> Kitchen Storage Rack-Home | J9: PROD70 | K9: =VLOOKUP(Table1[[#This Row],[Store_ID]],Store_Dim!$A$3:$D$22,2,FALSE) -> Bean, Jones and Park-West | L9: STORE8 | M9: 1 | N9: 342.39 | O9: 0.23 | P9: PayPal | Q9: 1054.5612 | W9: Standard Error | X9: 18.323976
A10: SALE8 | B10: ="Q" &ROUNDUP(MONTH(E10)/3,0) -> Q2 | C10: =TEXT(Table1[[#This Row],[Order_Date]],"mmmm") -> May | D10: =YEAR(Table1[[#This Row],[Order_Date]]) -> 2025 | E10: 45781 | F10: =VLOOKUP(Table1[[#This Row],[Customer_ID]],Customer_Dim!$A$2:$H$501,2,FALSE) -> Dr. Suzanne Bullock | G10: =_xlfn.XLOOKUP(Table1[[#This Row],[Customer_ID]],Customer_Dim!$A$2:$A$501,Customer_Dim!$E$2:$E$501) -> Lake Blaketon | H10: CUST1187 | I10: =VLOOKUP(Table1[[#This Row],[Product_ID]],Product_Dim!$A$2:$G$101,2,FALSE) -> Stainless Steel Cookware Set-Home | J10: PROD99 | K10: =VLOOKUP(Table1[[#This Row],[Store_ID]],Store_Dim!$A$3:$D$22,2,FALSE) -> Gray Ltd-North | L10: STORE5 | M10: 1 | N10: 448.25 | O10: 0.07 | P10: PayPal | Q10: 1250.6175 | W10: Median | X10: 871.4193
A11: SALE9 | B11: ="Q" &ROUNDUP(MONTH(E11)/3,0) -> Q3 | C11: =TEXT(Table1[[#This Row],[Order_Date]],"mmmm") -> July | D11: =YEAR(Table1[[#This Row],[Order_Date]]) -> 2025 | E11: 45869 | F11: Unknown | G11: Unknown | H11: CUST1464 | I11: =VLOOKUP(Table1[[#This Row],[Product_ID]],Product_Dim!$A$2:$G$101,2,FALSE) -> Modern Wall Clock-Home | J11: PROD33 | K11: =VLOOKUP(Table1[[#This Row],[Store_ID]],Store_Dim!$A$3:$D$22,2,FALSE) -> Rivera-Warner-East | L11: STORE0 | M11: 1 | N11: 873.17 | O11: 0.23 | P11: PayPal | Q11: 1344.6818 | W11: Mode | X11: #N/A
A12: SALE10 | B12: ="Q" &ROUNDUP(MONTH(E12)/3,0) -> Q1 | C12: =TEXT(Table1[[#This Row],[Order_Date]],"mmmm") -> February | D12: =YEAR(Table1[[#This Row],[Order_Date]]) -> 2024 | E12: 45335 | F12: =VLOOKUP(Table1[[#This Row],[Customer_ID]],Customer_Dim!$A$2:$H$501,2,FALSE) -> Michael Thomas | G12: =_xlfn.XLOOKUP(Table1[[#This Row],[Customer_ID]],Customer_Dim!$A$2:$A$501,Customer_Dim!$E$2:$E$501) -> Woodmouth | H12: CUST1065 | I12: =VLOOKUP(Table1[[#This Row],[Product_ID]],Product_Dim!$A$2:$G$101,2,FALSE) -> Foldable Camping Chair-Sports | J12: PROD24 | K12: =VLOOKUP(Table1[[#This Row],[Store_ID]],Store_Dim!$A$3:$D$22,2,FALSE) -> Mcdonald Inc-South | L12: STORE14 | M12: 1 | N12: 278.63 | O12: 0.07 | P12: Credit Card | Q12: 259.1259 | W12: Standard Deviation | X12: 819.26822
A13: SALE11 | B13: ="Q" &ROUNDUP(MONTH(E13)/3,0) -> Q2 | C13: =TEXT(Table1[[#This Row],[Order_Date]],"mmmm") -> May | D13: =YEAR(Table1[[#This Row],[Order_Date]]) -> 2025 | E13: 45801 | F13: =VLOOKUP(Table1[[#This Row],[Customer_ID]],Customer_Dim!$A$2:$H$501,2,FALSE) -> Jessica Gonzalez | G13: =_xlfn.XLOOKUP(Table1[[#This Row],[Customer_ID]],Customer_Dim!$A$2:$A$501,Customer_Dim!$E$2:$E$501) -> South Darrenland | H13: CUST1320 | I13: =VLOOKUP(Table1[[#This Row],[Product_ID]],Product_Dim!$A$2:$G$101,2,FALSE) -> Portable Power Bank-Electronics | J13: PROD39 | K13: =VLOOKUP(Table1[[#This Row],[Store_ID]],Store_Dim!$A$3:$D$22,2,FALSE) -> Martinez, Adkins and Johnson-North | L13: STORE1 | M13: 1 | N13: 286.92 | O13: 0.17 | P13: Credit Card | Q13: 952.5744 | W13: Sample Variance | X13: 671200.41
A14: SALE12 | B14: ="Q" &ROUNDUP(MONTH(E14)/3,0) -> Q3 | C14: =TEXT(Table1[[#This Row],[Order_Date]],"mmmm") -> August | D14: =YEAR(Table1[[#This Row],[Order_Date]]) -> 2024 | E14: 45528 | F14: =VLOOKUP(Table1[[#This Row],[Customer_ID]],Customer_Dim!$A$2:$H$501,2,FALSE) -> Wesley Short | G14: =_xlfn.XLOOKUP(Table1[[#This Row],[Customer_ID]],Customer_Dim!$A$2:$A$501,Customer_Dim!$E$2:$E$501) -> Susanstad | H14: CUST1237 | I14: =VLOOKUP(Table1[[#This Row],[Product_ID]],Product_Dim!$A$2:$G$101,2,FALSE) -> Sports Wrist Sweatbands-Sports | J14: PROD88 | K14: =VLOOKUP(Table1[[#This Row],[Store_ID]],Store_Dim!$A$3:$D$22,2,FALSE) -> Alexander Group-South | L14: STORE4 | M14: 1 | N14: 644.58 | O14: 0.01 | P14: Credit Card | Q14: 2552.5368 | W14: Kurtosis | X14: 0.047375245 | Y14: (+ means Leptokurtic)
A15: SALE13 | B15: ="Q" &ROUNDUP(MONTH(E15)/3,0) -> Q3 | C15: =TEXT(Table1[[#This Row],[Order_Date]],"mmmm") -> August | D15: =YEAR(Table1[[#This Row],[Order_Date]]) -> 2025 | E15: 45875 | F15: =VLOOKUP(Table1[[#This Row],[Customer_ID]],Customer_Dim!$A$2:$H$501,2,FALSE) -> Adam Castro | G15: =_xlfn.XLOOKUP(Table1[[#This Row],[Customer_ID]],Customer_Dim!$A$2:$A$501,Customer_Dim!$E$2:$E$501) -> New Donnabury | H15: CUST1443 | I15: =VLOOKUP(Table1[[#This Row],[Product_ID]],Product_Dim!$A$2:$G$101,2,FALSE) -> Gaming Mechanical Keyboard-Electronics | J15: PROD34 | K15: =VLOOKUP(Table1[[#This Row],[Store_ID]],Store_Dim!$A$3:$D$22,2,FALSE) -> Frederick-Wright-West | L15: STORE16 | M15: 1 | N15: 316.9 | O15: 0.3 | P15: PayPal | Q15: 443.66 | W15: Skewness | X15: 0.8786739 | Y15: (Right Skew for + value)
A16: SALE14 | B16: ="Q" &ROUNDUP(MONTH(E16)/3,0) -> Q2 | C16: =TEXT(Table1[[#This Row],[Order_Date]],"mmmm") -> June | D16: =YEAR(Table1[[#This Row],[Order_Date]]) -> 2025 | E16: 45829 | F16: =VLOOKUP(Table1[[#This Row],[Customer_ID]],Customer_Dim!$A$2:$H$501,2,FALSE) -> Sherry Cabrera | G16: =_xlfn.XLOOKUP(Table1[[#This Row],[Customer_ID]],Customer_Dim!$A$2:$A$501,Customer_Dim!$E$2:$E$501) -> Shannonview | H16: CUST1348 | I16: =VLOOKUP(Table1[[#This Row],[Product_ID]],Product_Dim!$A$2:$G$101,2,FALSE) -> Foldable Camping Chair-Sports | J16: PROD24 | K16: =VLOOKUP(Table1[[#This Row],[Store_ID]],Store_Dim!$A$3:$D$22,2,FALSE) -> Shelton PLC-North | L16: STORE15 | M16: 1 | N16: 403.47 | O16: 0.29 | P16: PayPal | Q16: 1145.8548 | W16: Range | X16: 3889.7838
A17: SALE15 | B17: ="Q" &ROUNDUP(MONTH(E17)/3,0) -> Q4 | C17: =TEXT(Table1[[#This Row],[Order_Date]],"mmmm") -> December | D17: =YEAR(Table1[[#This Row],[Order_Date]]) -> 2024 | E17: 45636 | F17: =VLOOKUP(Table1[[#This Row],[Customer_ID]],Customer_Dim!$A$2:$H$501,2,FALSE) -> Lindsay Beasley | G17: =_xlfn.XLOOKUP(Table1[[#This Row],[Customer_ID]],Customer_Dim!$A$2:$A$501,Customer_Dim!$E$2:$E$501) -> Wesleyhaven | H17: CUST1435 | I17: =VLOOKUP(Table1[[#This Row],[Product_ID]],Product_Dim!$A$2:$G$101,2,FALSE) -> Women's Summer Dress-Clothing | J17: PROD36 | K17: =VLOOKUP(Table1[[#This Row],[Store_ID]],Store_Dim!$A$3:$D$22,2,FALSE) -> Moore, Padilla and Butler-South | L17: STORE9 | M17: 1 | N17: 871.34 | O17: 0.04 | P17: COD | Q17: 2509.4592 | W17: Minimum | X17: 18.459
A18: SALE16 | B18: ="Q" &ROUNDUP(MONTH(E18)/3,0) -> Q3 | C18: =TEXT(Table1[[#This Row],[Order_Date]],"mmmm") -> September | D18: =YEAR(Table1[[#This Row],[Order_Date]]) -> 2025 | E18: 45913 | F18: =VLOOKUP(Table1[[#This Row],[Customer_ID]],Customer_Dim!$A$2:$H$501,2,FALSE) -> Arthur Warren | G18: =_xlfn.XLOOKUP(Table1[[#This Row],[Customer_ID]],Customer_Dim!$A$2:$A$501,Customer_Dim!$E$2:$E$501) -> Ericshire | H18: CUST1276 | I18: =VLOOKUP(Table1[[#This Row],[Product_ID]],Product_Dim!$A$2:$G$101,2,FALSE) -> Adjustable Dumbbells 20kg-Sports | J18: PROD65 | K18: =VLOOKUP(Table1[[#This Row],[Store_ID]],Store_Dim!$A$3:$D$22,2,FALSE) -> Mann-Austin-East | L18: STORE19 | M18: 1 | N18: 451.98 | O18: 0.25 | P18: Credit Card | Q18: 677.97 | W18: Maximum | X18: 3908.2428
A19: SALE17 | B19: ="Q" &ROUNDUP(MONTH(E19)/3,0) -> Q4 | C19: =TEXT(Table1[[#This Row],[Order_Date]],"mmmm") -> December | D19: =YEAR(Table1[[#This Row],[Order_Date]]) -> 2024 | E19: 45637 | F19: =VLOOKUP(Table1[[#This Row],[Customer_ID]],Customer_Dim!$A$2:$H$501,2,FALSE) -> Molly Gardner | G19: =_xlfn.XLOOKUP(Table1[[#This Row],[Customer_ID]],Customer_Dim!$A$2:$A$501,Customer_Dim!$E$2:$E$501) -> Nicoleborough | H19: CUST1079 | I19: =VLOOKUP(Table1[[#This Row],[Product_ID]],Product_Dim!$A$2:$G$101,2,FALSE) -> Decorative Floor Vase-Home | J19: PROD27 | K19: =VLOOKUP(Table1[[#This Row],[Store_ID]],Store_Dim!$A$3:$D$22,2,FALSE) -> Alexander Group-South | L19: STORE4 | M19: 1 | N19: 502.69 | O19: 0.23 | P19: Credit Card | Q19: 774.1426 | W19: Sum | X19: 2175066.6
A20: SALE18 | B20: ="Q" &ROUNDUP(MONTH(E20)/3,0) -> Q3 | C20: =TEXT(Table1[[#This Row],[Order_Date]],"mmmm") -> August | D20: =YEAR(Table1[[#This Row],[Order_Date]]) -> 2024 | E20: 45517 | F20: =VLOOKUP(Table1[[#This Row],[Customer_ID]],Customer_Dim!$A$2:$H$501,2,FALSE) -> David Patterson | G20: =_xlfn.XLOOKUP(Table1[[#This Row],[Customer_ID]],Customer_Dim!$A$2:$A$501,Customer_Dim!$E$2:$E$501) -> New Amyport | H20: CUST1094 | I20: =VLOOKUP(Table1[[#This Row],[Product_ID]],Product_Dim!$A$2:$G$101,2,FALSE) -> Portable Power Bank-Electronics | J20: PROD39 | K20: =VLOOKUP(Table1[[#This Row],[Store_ID]],Store_Dim!$A$3:$D$22,2,FALSE) -> Alexander Group-South | L20: STORE4 | M20: 1 | N20: 559.23 | O20: 0.25 | P20: COD | Q20: 838.845 | W20: Count | X20: 1999
A21: SALE19 | B21: ="Q" &ROUNDUP(MONTH(E21)/3,0) -> Q1 | C21: =TEXT(Table1[[#This Row],[Order_Date]],"mmmm") -> March | D21: =YEAR(Table1[[#This Row],[Order_Date]]) -> 2024 | E21: 45369 | F21: =VLOOKUP(Table1[[#This Row],[Customer_ID]],Customer_Dim!$A$2:$H$501,2,FALSE) -> Maria Hill | G21: =_xlfn.XLOOKUP(Table1[[#This Row],[Customer_ID]],Customer_Dim!$A$2:$A$501,Customer_Dim!$E$2:$E$501) -> Zamoraborough | H21: CUST1239 | I21: =VLOOKUP(Table1[[#This Row],[Product_ID]],Product_Dim!$A$2:$G$101,2,FALSE) -> Luxury Perfume Spray-Beauty | J21: PROD60 | K21: =VLOOKUP(Table1[[#This Row],[Store_ID]],Store_Dim!$A$3:$D$22,2,FALSE) -> Gardner, Humphrey and Contreras-East | L21: STORE13 | M21: 1 | N21: 513.95973 | O21: 0.04 | P21: COD | Q21: 1782.4512
A22: SALE20 | B22: ="Q" &ROUNDUP(MONTH(E22)/3,0) -> Q3 | C22: =TEXT(Table1[[#This Row],[Order_Date]],"mmmm") -> July | D22: =YEAR(Table1[[#This Row],[Order_Date]]) -> 2025 | E22: 45843 | F22: =VLOOKUP(Table1[[#This Row],[Customer_ID]],Customer_Dim!$A$2:$H$501,2,FALSE) -> Justin Cross | G22: =_xlfn.XLOOKUP(Table1[[#This Row],[Customer_ID]],Customer_Dim!$A$2:$A$501,Customer_Dim!$E$2:$E$501) -> North Anthonychester | H22: CUST1144 | I22: =VLOOKUP(Table1[[#This Row],[Product_ID]],Product_Dim!$A$2:$G$101,2,FALSE) -> Professional Jump Rope-Sports | J22: PROD72 | K22: =VLOOKUP(Table1[[#This Row],[Store_ID]],Store_Dim!$A$3:$D$22,2,FALSE) -> Holloway Ltd-North | L22: STORE17 | M22: 1 | N22: 986.04 | O22: 0.27 | P22: COD | Q22: 2159.4276
A23: SALE21 | B23: ="Q" &ROUNDUP(MONTH(E23)/3,0) -> Q2 | C23: =TEXT(Table1[[#This Row],[Order_Date]],"mmmm") -> June | D23: =YEAR(Table1[[#This Row],[Order_Date]]) -> 2024 | E23: 45447 | F23: =VLOOKUP(Table1[[#This Row],[Customer_ID]],Customer_Dim!$A$2:$H$501,2,FALSE) -> Alexander Byrd | G23: =_xlfn.XLOOKUP(Table1[[#This Row],[Customer_ID]],Customer_Dim!$A$2:$A$501,Customer_Dim!$E$2:$E$501) -> Parkerview | H23: CUST1396 | I23: =VLOOKUP(Table1[[#This Row],[Product_ID]],Product_Dim!$A$2:$G$101,2,FALSE) -> USB External Hard Drive-Electronics | J23: PROD43 | K23: =VLOOKUP(Table1[[#This Row],[Store_ID]],Store_Dim!$A$3:$D$22,2,FALSE) -> Guerrero-Schmitt-East | L23: STORE18 | M23: 1 | N23: 589.56 | O23: 0.22 | P23: Credit Card | Q23: 459.8568
A24: SALE22 | B24: ="Q" &ROUNDUP(MONTH(E24)/3,0) -> Q2 | C24: =TEXT(Table1[[#This Row],[Order_Date]],"mmmm") -> April | D24: =YEAR(Table1[[#This Row],[Order_Date]]) -> 2024 | E24: 45394 | F24: =VLOOKUP(Table1[[#This Row],[Customer_ID]],Customer_Dim!$A$2:$H$501,2,FALSE) -> Elizabeth Foster | G24: =_xlfn.XLOOKUP(Table1[[#This Row],[Customer_ID]],Customer_Dim!$A$2:$A$501,Customer_Dim!$E$2:$E$501) -> Anthonymouth | H24: CUST1476 | I24: =VLOOKUP(Table1[[#This Row],[Product_ID]],Product_Dim!$A$2:$G$101,2,FALSE) -> Men's Sports Shorts-Clothing | J24: PROD69 | K24: =VLOOKUP(Table1[[#This Row],[Store_ID]],Store_Dim!$A$3:$D$22,2,FALSE) -> Hill, Wagner and Ballard-East | L24: STORE10 | M24: 1 | N24: 979.42 | O24: 0.03 | P24: PayPal | Q24: 2850.1122
A25: SALE23 | B25: ="Q" &ROUNDUP(MONTH(E25)/3,0) -> Q2 | C25: =TEXT(Table1[[#This Row],[Order_Date]],"mmmm") -> June | D25: =YEAR(Table1[[#This Row],[Order_Date]]) -> 2024 | E25: 45466 | F25: =VLOOKUP(Table1[[#This Row],[Customer_ID]],Customer_Dim!$A$2:$H$501,2,FALSE) -> Miranda King | G25: =_xlfn.XLOOKUP(Table1[[#This Row],[Customer_ID]],Customer_Dim!$A$2:$A$501,Customer_Dim!$E$2:$E$501) -> West Mathew | H25: CUST1368 | I25: =VLOOKUP(Table1[[#This Row],[Product_ID]],Product_Dim!$A$2:$G$101,2,FALSE) -> Hair Strengthening Shampoo-Beauty | J25: PROD12 | K25: =VLOOKUP(Table1[[#This Row],[Store_ID]],Store_Dim!$A$3:$D$22,2,FALSE) -> Bean, Jones and Park-West | L25: STORE8 | M25: 1 | N25: 719.28 | O25: 0.08 | P25: Credit Card | Q25: 661.7376
A26: SALE24 | B26: ="Q" &ROUNDUP(MONTH(E26)/3,0) -> Q3 | C26: =TEXT(Table1[[#This Row],[Order_Date]],"mmmm") -> September | D26: =YEAR(Table1[[#This Row],[Order_Date]]) -> 2025 | E26: 45908 | F26: =VLOOKUP(Table1[[#This Row],[Customer_ID]],Customer_Dim!$A$2:$H$501,2,FALSE) -> Jennifer Pruitt | G26: =_xlfn.XLOOKUP(Table1[[#This Row],[Customer_ID]],Customer_Dim!$A$2:$A$501,Customer_Dim!$E$2:$E$501) -> East Justin | H26: CUST1186 | I26: =VLOOKUP(Table1[[#This Row],[Product_ID]],Product_Dim!$A$2:$G$101,2,FALSE) -> Smart LED Light Strip-Electronics | J26: PROD67 | K26: =VLOOKUP(Table1[[#This Row],[Store_ID]],Store_Dim!$A$3:$D$22,2,FALSE) -> Benson-Elliott-East | L26: STORE6 | M26: 1 | N26: 77.6 | O26: 0.07 | P26: Credit Card | Q26: 216.504
A27: SALE25 | B27: ="Q" &ROUNDUP(MONTH(E27)/3,0) -> Q3 | C27: =TEXT(Table1[[#This Row],[Order_Date]],"mmmm") -> September | D27: =YEAR(Table1[[#This Row],[Order_Date]]) -> 2024 | E27: 45552 | F27: =VLOOKUP(Table1[[#This Row],[Customer_ID]],Customer_Dim!$A$2:$H$501,2,FALSE) -> Erika Padilla | G27: =_xlfn.XLOOKUP(Table1[[#This Row],[Customer_ID]],Customer_Dim!$A$2:$A$501,Customer_Dim!$E$2:$E$501) -> Andrewsland | H27: CUST1381 | I27: =VLOOKUP(Table1[[#This Row],[Product_ID]],Product_Dim!$A$2:$G$101,2,FALSE) -> Men's Leather Belt-Clothing | J27: PROD5 | K27: =VLOOKUP(Table1[[#This Row],[Store_ID]],Store_Dim!$A$3:$D$22,2,FALSE) -> Johnson-Wright-North | L27: STORE3 | M27: 1 | N27: 852.71 | O27: 0.14 | P27: PayPal | Q27: 2933.3224
A28: SALE26 | B28: ="Q" &ROUNDUP(MONTH(E28)/3,0) -> Q1 | C28: =TEXT(Table1[[#This Row],[Order_Date]],"mmmm") -> January | D28: =YEAR(Table1[[#This Row],[Order_Date]]) -> 2024 | E28: 45294 | F28: =VLOOKUP(Table1[[#This Row],[Customer_ID]],Customer_Dim!$A$2:$H$501,2,FALSE) -> Stuart Johnson | G28: =_xlfn.XLOOKUP(Table1[[#This Row],[Customer_ID]],Customer_Dim!$A$2:$A$501,Customer_Dim!$E$2:$E$501) -> West Markport | H28: CUST1213 | I28: =VLOOKUP(Table1[[#This Row],[Product_ID]],Product_Dim!$A$2:$G$101,2,FALSE) -> Portable Bluetooth Speaker-Electronics | J28: PROD98 | K28: =VLOOKUP(Table1[[#This Row],[Store_ID]],Store_Dim!$A$3:$D$22,2,FALSE) -> Bean, Jones and Park-West | L28: STORE8 | M28: 1 | N28: 156.16 | O28: 0.14953799 | P28: Credit Card | Q28: 599.6544
A29: SALE27 | B29: ="Q" &ROUNDUP(MONTH(E29)/3,0) -> Q1 | C29: =TEXT(Table1[[#This Row],[Order_Date]],"mmmm") -> February | D29: =YEAR(Table1[[#This Row],[Order_Date]]) -> 2025 | E29: 45710 | F29: =VLOOKUP(Table1[[#This Row],[Customer_ID]],Customer_Dim!$A$2:$H$501,2,FALSE) -> Anna Perez | G29: =_xlfn.XLOOKUP(Table1[[#This Row],[Customer_ID]],Customer_Dim!$A$2:$A$501,Customer_Dim!$E$2:$E$501) -> South Jerry | H29: CUST1200 | I29: =VLOOKUP(Table1[[#This Row],[Product_ID]],Product_Dim!$A$2:$G$101,2,FALSE) -> WiFi Mesh Router-Electronics | J29: PROD77 | K29: =VLOOKUP(Table1[[#This Row],[Store_ID]],Store_Dim!$A$3:$D$22,2,FALSE) -> Bean, Jones and Park-West | L29: STORE8 | M29: 1 | N29: 815.49 | O29: 0.17 | P29: Credit Card | Q29: 2030.5701
A30: SALE28 | B30: ="Q" &ROUNDUP(MONTH(E30)/3,0) -> Q3 | C30: =TEXT(Table1[[#This Row],[Order_Date]],"mmmm") -> September | D30: =YEAR(Table1[[#This Row],[Order_Date]]) -> 2025 | E30: 45923 | F30: =VLOOKUP(Table1[[#This Row],[Customer_ID]],Customer_Dim!$A$2:$H$501,2,FALSE) -> Theresa Campbell | G30: =_xlfn.XLOOKUP(Table1[[#This Row],[Customer_ID]],Customer_Dim!$A$2:$A$501,Customer_Dim!$E$2:$E$501) -> New Brian | H30: CUST1148 | I30: =VLOOKUP(Table1[[#This Row],[Product_ID]],Product_Dim!$A$2:$G$101,2,FALSE) -> USB-C Fast Charger-Electronics | J30: PROD13 | K30: =VLOOKUP(Table1[[#This Row],[Store_ID]],Store_Dim!$A$3:$D$22,2,FALSE) -> Black-Horn-South | L30: STORE2 | M30: 1 | N30: 74.21 | O30: 0.11 | P30: PayPal | Q30: 132.0938
A31: SALE29 | B31: ="Q" &ROUNDUP(MONTH(E31)/3,0) -> Q1 | C31: =TEXT(Table1[[#This Row],[Order_Date]],"mmmm") -> January | D31: =YEAR(Table1[[#This Row],[Order_Date]]) -> 2024 | E31: 45302 | F31: =VLOOKUP(Table1[[#This Row],[Customer_ID]],Customer_Dim!$A$2:$H$501,2,FALSE) -> Sherry Cabrera | G31: =_xlfn.XLOOKUP(Table1[[#This Row],[Customer_ID]],Customer_Dim!$A$2:$A$501,Customer_Dim!$E$2:$E$501) -> Shannonview | H31: CUST1348 | I31: =VLOOKUP(Table1[[#This Row],[Product_ID]],Product_Dim!$A$2:$G$101,2,FALSE) -> Stainless Steel Cookware Set-Home | J31: PROD99 | K31: =VLOOKUP(Table1[[#This Row],[Store_ID]],Store_Dim!$A$3:$D$22,2,FALSE) -> Johnson-Wright-North | L31: STORE3 | M31: 1 | N31: 451.67 | O31: 0.15 | P31: Credit Card | Q31: 1535.678
A32: SALE30 | B32: ="Q" &ROUNDUP(MONTH(E32)/3,0) -> Q4 | C32: =TEXT(Table1[[#This Row],[Order_Date]],"mmmm") -> October | D32: =YEAR(Table1[[#This Row],[Order_Date]]) -> 2023 | E32: 45217 | F32: =VLOOKUP(Table1[[#This Row],[Customer_ID]],Customer_Dim!$A$2:$H$501,2,FALSE) -> Joshua Ryan | G32: =_xlfn.XLOOKUP(Table1[[#This Row],[Customer_ID]],Customer_Dim!$A$2:$A$501,Customer_Dim!$E$2:$E$501) -> New David | H32: CUST1028 | I32: =VLOOKUP(Table1[[#This Row],[Product_ID]],Product_Dim!$A$2:$G$101,2,FALSE) -> Men's Leather Belt-Clothing | J32: PROD5 | K32: =VLOOKUP(Table1[[#This Row],[Store_ID]],Store_Dim!$A$3:$D$22,2,FALSE) -> Mann-Austin-East | L32: STORE19 | M32: 1 | N32: 429.38 | O32: 0.13 | P32: PayPal | Q32: 373.5606
... A63: SALE61 | B63: ="Q" &ROUNDUP(MONTH(E63)/3,0) -> Q1 | C63: =TEXT(Table1[[#This Row],[Order_Date]],"mmmm") -> February | D63: =YEAR(Table1[[#This Row],[Order_Date]]) -> 2025 | E63: 45716 | F63: =VLOOKUP(Table1[[#This Row],[Customer_ID]],Customer_Dim!$A$2:$H$501,2,FALSE) -> Maria Hill | G63: =_xlfn.XLOOKUP(Table1[[#This Row],[Customer_ID]],Customer_Dim!$A$2:$A$501,Customer_Dim!$E$2:$E$501) -> Zamoraborough | H63: CUST1239 | I63: =VLOOKUP(Table1[[#This Row],[Product_ID]],Product_Dim!$A$2:$G$101,2,FALSE) -> Knee Support Brace-Sports | J63: PROD19 | K63: =VLOOKUP(Table1[[#This Row],[Store_ID]],Store_Dim!$A$3:$D$22,2,FALSE) -> Martinez-Mullins-South | L63: STORE7 | M63: 1 | N63: 374.92 | O63: 0.18 | P63: PayPal | Q63: 307.4344
A64: SALE62 | B64: ="Q" &ROUNDUP(MONTH(E64)/3,0) -> Q3 | C64: =TEXT(Table1[[#This Row],[Order_Date]],"mmmm") -> August | D64: =YEAR(Table1[[#This Row],[Order_Date]]) -> 2024 | E64: 45515 | F64: Unknown | G64: Unknown | H64: CUST1464 | I64: =VLOOKUP(Table1[[#This Row],[Product_ID]],Product_Dim!$A$2:$G$101,2,FALSE) -> USB-C Laptop Charger-Electronics | J64: PROD93 | K64: =VLOOKUP(Table1[[#This Row],[Store_ID]],Store_Dim!$A$3:$D$22,2,FALSE) -> Frederick-Wright-West | L64: STORE16 | M64: 1 | N64: 468.94 | O64: 0.12 | P64: Credit Card | Q64: 412.6672
A65: SALE63 | B65: ="Q" &ROUNDUP(MONTH(E65)/3,0) -> Q3 | C65: =TEXT(Table1[[#This Row],[Order_Date]],"mmmm") -> September | D65: =YEAR(Table1[[#This Row],[Order_Date]]) -> 2025 | E65: 45927 | F65: =VLOOKUP(Table1[[#This Row],[Customer_ID]],Customer_Dim!$A$2:$H$501,2,FALSE) -> James Wolfe | G65: =_xlfn.XLOOKUP(Table1[[#This Row],[Customer_ID]],Customer_Dim!$A$2:$A$501,Customer_Dim!$E$2:$E$501) -> Benjaminton | H65: CUST1126 | I65: =VLOOKUP(Table1[[#This Row],[Product_ID]],Product_Dim!$A$2:$G$101,2,FALSE) -> Face Foundation Kit-Beauty | J65: PROD89 | K65: =VLOOKUP(Table1[[#This Row],[Store_ID]],Store_Dim!$A$3:$D$22,2,FALSE) -> Thomas, Bridges and Harris-North | L65: STORE12 | M65: 1 | N65: 121.37 | O65: 0.05 | P65: Credit Card | Q65: 230.603
A66: SALE64 | B66: ="Q" &ROUNDUP(MONTH(E66)/3,0) -> Q3 | C66: =TEXT(Table1[[#This Row],[Order_Date]],"mmmm") -> September | D66: =YEAR(Table1[[#This Row],[Order_Date]]) -> 2025 | E66: 45914 | F66: =VLOOKUP(Table1[[#This Row],[Customer_ID]],Customer_Dim!$A$2:$H$501,2,FALSE) -> Damon Perez | G66: =_xlfn.XLOOKUP(Table1[[#This Row],[Customer_ID]],Customer_Dim!$A$2:$A$501,Customer_Dim!$E$2:$E$501) -> Jasonton | H66: CUST1255 | I66: =VLOOKUP(Table1[[#This Row],[Product_ID]],Product_Dim!$A$2:$G$101,2,FALSE) -> Men's Track Pants-Clothing | J66: PROD53 | K66: =VLOOKUP(Table1[[#This Row],[Store_ID]],Store_Dim!$A$3:$D$22,2,FALSE) -> Hill, Wagner and Ballard-East | L66: STORE10 | M66: 1 | N66: 480.06 | O66: 0.01 | P66: Credit Card | Q66: 1088.6371
A67: SALE65 | B67: ="Q" &ROUNDUP(MONTH(E67)/3,0) -> Q4 | C67: =TEXT(Table1[[#This Row],[Order_Date]],"mmmm") -> December | D67: =YEAR(Table1[[#This Row],[Order_Date]]) -> 2023 | E67: 45290 | F67: =VLOOKUP(Table1[[#This Row],[Customer_ID]],Customer_Dim!$A$2:$H$501,2,FALSE) -> Mariah Brown | G67: =_xlfn.XLOOKUP(Table1[[#This Row],[Customer_ID]],Customer_Dim!$A$2:$A$501,Customer_Dim!$E$2:$E$501) -> Palmerbury | H67: CUST1162 | I67: =VLOOKUP(Table1[[#This Row],[Product_ID]],Product_Dim!$A$2:$G$101,2,FALSE) -> Stainless Steel Cookware Set-Home | J67: PROD99 | K67: =VLOOKUP(Table1[[#This Row],[Store_ID]],Store_Dim!$A$3:$D$22,2,FALSE) -> Holloway Ltd-North | L67: STORE17 | M67: 1 | N67: 856.57 | O67: 0.24 | P67: Credit Card | Q67: 1301.9864
A68: SALE66 | B68: ="Q" &ROUNDUP(MONTH(E68)/3,0) -> Q4 | C68: =TEXT(Table1[[#This Row],[Order_Date]],"mmmm") -> October | D68: =YEAR(Table1[[#This Row],[Order_Date]]) -> 2023 | E68: 45213 | F68: =VLOOKUP(Table1[[#This Row],[Customer_ID]],Customer_Dim!$A$2:$H$501,2,FALSE) -> Tyrone Olson | G68: =_xlfn.XLOOKUP(Table1[[#This Row],[Customer_ID]],Customer_Dim!$A$2:$A$501,Customer_Dim!$E$2:$E$501) -> Emilytown | H68: CUST1269 | I68: =VLOOKUP(Table1[[#This Row],[Product_ID]],Product_Dim!$A$2:$G$101,2,FALSE) -> WiFi Mesh Router-Electronics | J68: PROD77 | K68: =VLOOKUP(Table1[[#This Row],[Store_ID]],Store_Dim!$A$3:$D$22,2,FALSE) -> Black-Horn-South | L68: STORE2 | M68: 1 | N68: 814.25 | O68: 0.18 | P68: Credit Card | Q68: 2670.74
A69: SALE67 | B69: ="Q" &ROUNDUP(MONTH(E69)/3,0) -> Q4 | C69: =TEXT(Table1[[#This Row],[Order_Date]],"mmmm") -> November | D69: =YEAR(Table1[[#This Row],[Order_Date]]) -> 2023 | E69: 45255 | F69: =VLOOKUP(Table1[[#This Row],[Customer_ID]],Customer_Dim!$A$2:$H$501,2,FALSE) -> Sarah Smith | G69: =_xlfn.XLOOKUP(Table1[[#This Row],[Customer_ID]],Customer_Dim!$A$2:$A$501,Customer_Dim!$E$2:$E$501) -> East Rodney | H69: CUST1483 | I69: =VLOOKUP(Table1[[#This Row],[Product_ID]],Product_Dim!$A$2:$G$101,2,FALSE) -> Hair Strengthening Shampoo-Beauty | J69: PROD12 | K69: =VLOOKUP(Table1[[#This Row],[Store_ID]],Store_Dim!$A$3:$D$22,2,FALSE) -> Black-Horn-South | L69: STORE2 | M69: 1 | N69: 989.17 | O69: 0.2 | P69: PayPal | Q69: 791.336
A70: SALE68 | B70: ="Q" &ROUNDUP(MONTH(E70)/3,0) -> Q4 | C70: =TEXT(Table1[[#This Row],[Order_Date]],"mmmm") -> December | D70: =YEAR(Table1[[#This Row],[Order_Date]]) -> 2023 | E70: 45270 | F70: =VLOOKUP(Table1[[#This Row],[Customer_ID]],Customer_Dim!$A$2:$H$501,2,FALSE) -> Jacqueline Anthony | G70: =_xlfn.XLOOKUP(Table1[[#This Row],[Customer_ID]],Customer_Dim!$A$2:$A$501,Customer_Dim!$E$2:$E$501) -> Vincentside | H70: CUST1372 | I70: =VLOOKUP(Table1[[#This Row],[Product_ID]],Product_Dim!$A$2:$G$101,2,FALSE) -> Professional Jump Rope-Sports | J70: PROD72 | K70: =VLOOKUP(Table1[[#This Row],[Store_ID]],Store_Dim!$A$3:$D$22,2,FALSE) -> Hill, Wagner and Ballard-East | L70: STORE10 | M70: 1 | N70: 62.48 | O70: 0.18 | P70: Credit Card | Q70: 204.9344
A71: SALE69 | B71: ="Q" &ROUNDUP(MONTH(E71)/3,0) -> Q3 | C71: =TEXT(Table1[[#This Row],[Order_Date]],"mmmm") -> August | D71: =YEAR(Table1[[#This Row],[Order_Date]]) -> 2025 | E71: 45897 | F71: =VLOOKUP(Table1[[#This Row],[Customer_ID]],Customer_Dim!$A$2:$H$501,2,FALSE) -> Rebecca Baker | G71: =_xlfn.XLOOKUP(Table1[[#This Row],[Customer_ID]],Customer_Dim!$A$2:$A$501,Customer_Dim!$E$2:$E$501) -> New Katherine | H71: CUST1423 | I71: =VLOOKUP(Table1[[#This Row],[Product_ID]],Product_Dim!$A$2:$G$101,2,FALSE) -> USB-C Fast Charger-Electronics | J71: PROD13 | K71: =VLOOKUP(Table1[[#This Row],[Store_ID]],Store_Dim!$A$3:$D$22,2,FALSE) -> Frederick-Wright-West | L71: STORE16 | M71: 1 | N71: 561.24 | O71: 0.24 | P71: Credit Card | Q71: 1706.1696
A72: SALE70 | B72: ="Q" &ROUNDUP(MONTH(E72)/3,0) -> Q3 | C72: =TEXT(Table1[[#This Row],[Order_Date]],"mmmm") -> July | D72: =YEAR(Table1[[#This Row],[Order_Date]]) -> 2025 | E72: 45849 | F72: =VLOOKUP(Table1[[#This Row],[Customer_ID]],Customer_Dim!$A$2:$H$501,2,FALSE) -> Cheryl Copeland | G72: =_xlfn.XLOOKUP(Table1[[#This Row],[Customer_ID]],Customer_Dim!$A$2:$A$501,Customer_Dim!$E$2:$E$501) -> Snowmouth | H72: CUST1058 | I72: =VLOOKUP(Table1[[#This Row],[Product_ID]],Product_Dim!$A$2:$G$101,2,FALSE) -> Luxury Perfume Spray-Beauty | J72: PROD60 | K72: =VLOOKUP(Table1[[#This Row],[Store_ID]],Store_Dim!$A$3:$D$22,2,FALSE) -> Gray Ltd-North | L72: STORE5 | M72: 1 | N72: 92.24 | O72: 0.28 | P72: COD | Q72: 1087.9978
A73: SALE71 | B73: ="Q" &ROUNDUP(MONTH(E73)/3,0) -> Q3 | C73: =TEXT(Table1[[#This Row],[Order_Date]],"mmmm") -> August | D73: =YEAR(Table1[[#This Row],[Order_Date]]) -> 2025 | E73: 45889 | F73: =VLOOKUP(Table1[[#This Row],[Customer_ID]],Customer_Dim!$A$2:$H$501,2,FALSE) -> Daniel Contreras | G73: =_xlfn.XLOOKUP(Table1[[#This Row],[Customer_ID]],Customer_Dim!$A$2:$A$501,Customer_Dim!$E$2:$E$501) -> Robertview | H73: CUST1168 | I73: =VLOOKUP(Table1[[#This Row],[Product_ID]],Product_Dim!$A$2:$G$101,2,FALSE) -> Professional Jump Rope-Sports | J73: PROD72 | K73: =VLOOKUP(Table1[[#This Row],[Store_ID]],Store_Dim!$A$3:$D$22,2,FALSE) -> Martinez, Adkins and Johnson-North | L73: STORE1 | M73: 1 | N73: 668.3 | O73: 0.07 | P73: Credit Card | Q73: 1243.038
A74: SALE72 | B74: ="Q" &ROUNDUP(MONTH(E74)/3,0) -> Q3 | C74: =TEXT(Table1[[#This Row],[Order_Date]],"mmmm") -> August | D74: =YEAR(Table1[[#This Row],[Order_Date]]) -> 2024 | E74: 45533 | F74: =VLOOKUP(Table1[[#This Row],[Customer_ID]],Customer_Dim!$A$2:$H$501,2,FALSE) -> Sarah Smith | G74: =_xlfn.XLOOKUP(Table1[[#This Row],[Customer_ID]],Customer_Dim!$A$2:$A$501,Customer_Dim!$E$2:$E$501) -> Kathleenport | H74: CUST1409 | I74: =VLOOKUP(Table1[[#This Row],[Product_ID]],Product_Dim!$A$2:$G$101,2,FALSE) -> Sports Water Hydration Pack-Sports | J74: PROD38 | K74: =VLOOKUP(Table1[[#This Row],[Store_ID]],Store_Dim!$A$3:$D$22,2,FALSE) -> Gray Ltd-North | L74: STORE5 | M74: 1 | N74: 553.82 | O74: 0.09 | P74: Credit Card | Q74: 503.9762
A75: SALE73 | B75: ="Q" &ROUNDUP(MONTH(E75)/3,0) -> Q4 | C75: =TEXT(Table1[[#This Row],[Order_Date]],"mmmm") -> November | D75: =YEAR(Table1[[#This Row],[Order_Date]]) -> 2024 | E75: 45626 | F75: =VLOOKUP(Table1[[#This Row],[Customer_ID]],Customer_Dim!$A$2:$H$501,2,FALSE) -> Christopher Carter | G75: =_xlfn.XLOOKUP(Table1[[#This Row],[Customer_ID]],Customer_Dim!$A$2:$A$501,Customer_Dim!$E$2:$E$501) -> Brendastad | H75: CUST1037 | I75: =VLOOKUP(Table1[[#This Row],[Product_ID]],Product_Dim!$A$2:$G$101,2,FALSE) -> High-Grip Football-Sports | J75: PROD45 | K75: =VLOOKUP(Table1[[#This Row],[Store_ID]],Store_Dim!$A$3:$D$22,2,FALSE) -> Aguirre-Keller-South | L75: STORE11 | M75: 1 | N75: 556.43 | O75: 0.13 | P75: Credit Card | Q75: 968.1882
A76: SALE74 | B76: ="Q" &ROUNDUP(MONTH(E76)/3,0) -> Q4 | C76: =TEXT(Table1[[#This Row],[Order_Date]],"mmmm") -> October | D76: =YEAR(Table1[[#This Row],[Order_Date]]) -> 2025 | E76: 45942 | F76: =VLOOKUP(Table1[[#This Row],[Customer_ID]],Customer_Dim!$A$2:$H$501,2,FALSE) -> Samantha Robinson | G76: =_xlfn.XLOOKUP(Table1[[#This Row],[Customer_ID]],Customer_Dim!$A$2:$A$501,Customer_Dim!$E$2:$E$501) -> North Roy | H76: CUST1273 | I76: =VLOOKUP(Table1[[#This Row],[Product_ID]],Product_Dim!$A$2:$G$101,2,FALSE) -> Outdoor Sports Water Bottle-Sports | J76: PROD20 | K76: =VLOOKUP(Table1[[#This Row],[Store_ID]],Store_Dim!$A$3:$D$22,2,FALSE) -> Bean, Jones and Park-West | L76: STORE8 | M76: 1 | N76: 184.98 | O76: 0.1 | P76: COD | Q76: 166.482
... A97: SALE95 | B97: ="Q" &ROUNDUP(MONTH(E97)/3,0) -> Q3 | C97: =TEXT(Table1[[#This Row],[Order_Date]],"mmmm") -> September | D97: =YEAR(Table1[[#This Row],[Order_Date]]) -> 2024 | E97: 45556 | F97: =VLOOKUP(Table1[[#This Row],[Customer_ID]],Customer_Dim!$A$2:$H$501,2,FALSE) -> Darren Burton | G97: =_xlfn.XLOOKUP(Table1[[#This Row],[Customer_ID]],Customer_Dim!$A$2:$A$501,Customer_Dim!$E$2:$E$501) -> Lake Alice | H97: CUST1321 | I97: =VLOOKUP(Table1[[#This Row],[Product_ID]],Product_Dim!$A$2:$G$101,2,FALSE) -> Stainless Steel Cookware Set-Home | J97: PROD99 | K97: =VLOOKUP(Table1[[#This Row],[Store_ID]],Store_Dim!$A$3:$D$22,2,FALSE) -> Benson-Elliott-East | L97: STORE6 | M97: 1 | N97: 68.29 | O97: 0.14 | P97: COD | Q97: 117.4588
A98: SALE96 | B98: ="Q" &ROUNDUP(MONTH(E98)/3,0) -> Q3 | C98: =TEXT(Table1[[#This Row],[Order_Date]],"mmmm") -> August | D98: =YEAR(Table1[[#This Row],[Order_Date]]) -> 2024 | E98: 45523 | F98: =VLOOKUP(Table1[[#This Row],[Customer_ID]],Customer_Dim!$A$2:$H$501,2,FALSE) -> Nancy Page | G98: =_xlfn.XLOOKUP(Table1[[#This Row],[Customer_ID]],Customer_Dim!$A$2:$A$501,Customer_Dim!$E$2:$E$501) -> West Julia | H98: CUST1244 | I98: =VLOOKUP(Table1[[#This Row],[Product_ID]],Product_Dim!$A$2:$G$101,2,FALSE) -> Boxing Hand Wraps-Sports | J98: PROD50 | K98: =VLOOKUP(Table1[[#This Row],[Store_ID]],Store_Dim!$A$3:$D$22,2,FALSE) -> Hill, Wagner and Ballard-East | L98: STORE10 | M98: 1 | N98: 842.9 | O98: 0.06 | P98: COD | Q98: 792.326
A99: SALE97 | B99: ="Q" &ROUNDUP(MONTH(E99)/3,0) -> Q4 | C99: =TEXT(Table1[[#This Row],[Order_Date]],"mmmm") -> October | D99: =YEAR(Table1[[#This Row],[Order_Date]]) -> 2024 | E99: 45587 | F99: =VLOOKUP(Table1[[#This Row],[Customer_ID]],Customer_Dim!$A$2:$H$501,2,FALSE) -> Cynthia Roberts | G99: =_xlfn.XLOOKUP(Table1[[#This Row],[Customer_ID]],Customer_Dim!$A$2:$A$501,Customer_Dim!$E$2:$E$501) -> Millerfort | H99: CUST1287 | I99: =VLOOKUP(Table1[[#This Row],[Product_ID]],Product_Dim!$A$2:$G$101,2,FALSE) -> Men's Running Jacket-Clothing | J99: PROD3 | K99: =VLOOKUP(Table1[[#This Row],[Store_ID]],Store_Dim!$A$3:$D$22,2,FALSE) -> Johnson-Wright-North | L99: STORE3 | M99: 3 | N99: 751.94 | O99: 0.26 | P99: PayPal | Q99: 1669.3068
A100: SALE98 | B100: ="Q" &ROUNDUP(MONTH(E100)/3,0) -> Q4 | C100: =TEXT(Table1[[#This Row],[Order_Date]],"mmmm") -> October | D100: =YEAR(Table1[[#This Row],[Order_Date]]) -> 2024 | E100: 45580 | F100: =VLOOKUP(Table1[[#This Row],[Customer_ID]],Customer_Dim!$A$2:$H$501,2,FALSE) -> Joseph Richards | G100: =_xlfn.XLOOKUP(Table1[[#This Row],[Customer_ID]],Customer_Dim!$A$2:$A$501,Customer_Dim!$E$2:$E$501) -> Wigginsville | H100: CUST1131 | I100: =VLOOKUP(Table1[[#This Row],[Product_ID]],Product_Dim!$A$2:$G$101,2,FALSE) -> Premium Blanket Throw-Home | J100: PROD56 | K100: =VLOOKUP(Table1[[#This Row],[Store_ID]],Store_Dim!$A$3:$D$22,2,FALSE) -> Martinez-Mullins-South | L100: STORE7 | M100: 4 | N100: 476.28 | O100: 0.17 | P100: Credit Card | Q100: 1581.2496
A101: SALE99 | B101: ="Q" &ROUNDUP(MONTH(E101)/3,0) -> Q3 | C101: =TEXT(Table1[[#This Row],[Order_Date]],"mmmm") -> July | D101: =YEAR(Table1[[#This Row],[Order_Date]]) -> 2024 | E101: 45479 | F101: =VLOOKUP(Table1[[#This Row],[Customer_ID]],Customer_Dim!$A$2:$H$501,2,FALSE) -> Andrew Smith | G101: =_xlfn.XLOOKUP(Table1[[#This Row],[Customer_ID]],Customer_Dim!$A$2:$A$501,Customer_Dim!$E$2:$E$501) -> East Matthew | H101: CUST1325 | I101: =VLOOKUP(Table1[[#This Row],[Product_ID]],Product_Dim!$A$2:$G$101,2,FALSE) -> Sports Stopwatch Pro-Sports | J101: PROD54 | K101: =VLOOKUP(Table1[[#This Row],[Store_ID]],Store_Dim!$A$3:$D$22,2,FALSE) -> Johnson-Wright-North | L101: STORE3 | M101: 3 | N101: 541.99 | O101: 0.24 | P101: COD | Q101: 1235.7372
A102: SALE100 | B102: ="Q" &ROUNDUP(MONTH(E102)/3,0) -> Q1 | C102: =TEXT(Table1[[#This Row],[Order_Date]],"mmmm") -> January | D102: =YEAR(Table1[[#This Row],[Order_Date]]) -> 2025 | E102: 45677 | F102: =VLOOKUP(Table1[[#This Row],[Customer_ID]],Customer_Dim!$A$2:$H$501,2,FALSE) -> Gregory Allen | G102: =_xlfn.XLOOKUP(Table1[[#This Row],[Customer_ID]],Customer_Dim!$A$2:$A$501,Customer_Dim!$E$2:$E$501) -> West Bruce | H102: CUST1369 | I102: =VLOOKUP(Table1[[#This Row],[Product_ID]],Product_Dim!$A$2:$G$101,2,FALSE) -> Modern Wall Clock-Home | J102: PROD33 | K102: =VLOOKUP(Table1[[#This Row],[Store_ID]],Store_Dim!$A$3:$D$22,2,FALSE) -> Gray Ltd-North | L102: STORE5 | M102: 2 | N102: 401.5 | O102: 0.18 | P102: Credit Card | Q102: 658.46
A103: SALE101 | B103: ="Q" &ROUNDUP(MONTH(E103)/3,0) -> Q2 | C103: =TEXT(Table1[[#This Row],[Order_Date]],"mmmm") -> June | D103: =YEAR(Table1[[#This Row],[Order_Date]]) -> 2024 | E103: 45453 | F103: =VLOOKUP(Table1[[#This Row],[Customer_ID]],Customer_Dim!$A$2:$H$501,2,FALSE) -> Christy Hoffman | G103: =_xlfn.XLOOKUP(Table1[[#This Row],[Customer_ID]],Customer_Dim!$A$2:$A$501,Customer_Dim!$E$2:$E$501) -> Garyberg | H103: CUST1084 | I103: =VLOOKUP(Table1[[#This Row],[Product_ID]],Product_Dim!$A$2:$G$101,2,FALSE) -> Women's Scarf Set-Clothing | J103: PROD25 | K103: =VLOOKUP(Table1[[#This Row],[Store_ID]],Store_Dim!$A$3:$D$22,2,FALSE) -> Gardner, Humphrey and Contreras-East | L103: STORE13 | M103: 3 | N103: 359.56 | O103: 0.17 | P103: PayPal | Q103: 895.3044
A104: SALE102 | B104: ="Q" &ROUNDUP(MONTH(E104)/3,0) -> Q3 | C104: =TEXT(Table1[[#This Row],[Order_Date]],"mmmm") -> September | D104: =YEAR(Table1[[#This Row],[Order_Date]]) -> 2024 | E104: 45552 | F104: =VLOOKUP(Table1[[#This Row],[Customer_ID]],Customer_Dim!$A$2:$H$501,2,FALSE) -> David Cobb | G104: =_xlfn.XLOOKUP(Table1[[#This Row],[Customer_ID]],Customer_Dim!$A$2:$A$501,Customer_Dim!$E$2:$E$501) -> Lake Thomas | H104: CUST1097 | I104: =VLOOKUP(Table1[[#This Row],[Product_ID]],Product_Dim!$A$2:$G$101,2,FALSE) -> Wall-Mounted Spice Rack-Home | J104: PROD80 | K104: =VLOOKUP(Table1[[#This Row],[Store_ID]],Store_Dim!$A$3:$D$22,2,FALSE) -> Thomas, Bridges and Harris-North | L104: STORE12 | M104: 2 | N104: 471.88 | O104: 0.24 | P104: PayPal | Q104: 717.2576
A105: SALE103 | B105: ="Q" &ROUNDUP(MONTH(E105)/3,0) -> Q3 | C105: =TEXT(Table1[[#This Row],[Order_Date]],"mmmm") -> September | D105: =YEAR(Table1[[#This Row],[Order_Date]]) -> 2025 | E105: 45907 | F105: =VLOOKUP(Table1[[#This Row],[Customer_ID]],Customer_Dim!$A$2:$H$501,2,FALSE) -> Melissa Hamilton | G105: =_xlfn.XLOOKUP(Table1[[#This Row],[Customer_ID]],Customer_Dim!$A$2:$A$501,Customer_Dim!$E$2:$E$501) -> Hutchinsonville | H105: CUST1182 | I105: =VLOOKUP(Table1[[#This Row],[Product_ID]],Product_Dim!$A$2:$G$101,2,FALSE) -> Gaming Mechanical Keyboard-Electronics | J105: PROD34 | K105: =VLOOKUP(Table1[[#This Row],[Store_ID]],Store_Dim!$A$3:$D$22,2,FALSE) -> Alexander Group-South | L105: STORE4 | M105: 4 | N105: 925.19 | O105: 0.19 | P105: PayPal | Q105: 2997.6156
A106: SALE104 | B106: ="Q" &ROUNDUP(MONTH(E106)/3,0) -> Q1 | C106: =TEXT(Table1[[#This Row],[Order_Date]],"mmmm") -> February | D106: =YEAR(Table1[[#This Row],[Order_Date]]) -> 2024 | E106: 45330 | F106: =VLOOKUP(Table1[[#This Row],[Customer_ID]],Customer_Dim!$A$2:$H$501,2,FALSE) -> David Arnold | G106: =_xlfn.XLOOKUP(Table1[[#This Row],[Customer_ID]],Customer_Dim!$A$2:$A$501,Customer_Dim!$E$2:$E$501) -> East Jennifer | H106: CUST1029 | I106: =VLOOKUP(Table1[[#This Row],[Product_ID]],Product_Dim!$A$2:$G$101,2,FALSE) -> Kitchen Cutting Board-Home | J106: PROD86 | K106: =VLOOKUP(Table1[[#This Row],[Store_ID]],Store_Dim!$A$3:$D$22,2,FALSE) -> Aguirre-Keller-South | L106: STORE11 | M106: 2 | N106: 879.63 | O106: 0.07 | P106: COD | Q106: 1636.1118
A107: SALE105 | B107: ="Q" &ROUNDUP(MONTH(E107)/3,0) -> Q4 | C107: =TEXT(Table1[[#This Row],[Order_Date]],"mmmm") -> October | D107: =YEAR(Table1[[#This Row],[Order_Date]]) -> 2023 | E107: 45214 | F107: =VLOOKUP(Table1[[#This Row],[Customer_ID]],Customer_Dim!$A$2:$H$501,2,FALSE) -> Dr. Benjamin Price | G107: =_xlfn.XLOOKUP(Table1[[#This Row],[Customer_ID]],Customer_Dim!$A$2:$A$501,Customer_Dim!$E$2:$E$501) -> Kylebury | H107: CUST1002 | I107: =VLOOKUP(Table1[[#This Row],[Product_ID]],Product_Dim!$A$2:$G$101,2,FALSE) -> Decorative Lamp Shade-Home | J107: PROD79 | K107: =VLOOKUP(Table1[[#This Row],[Store_ID]],Store_Dim!$A$3:$D$22,2,FALSE) -> Holloway Ltd-North | L107: STORE17 | M107: 2 | N107: 418.23 | O107: 0.28 | P107: Credit Card | Q107: 602.2512
A108: SALE106 | B108: ="Q" &ROUNDUP(MONTH(E108)/3,0) -> Q3 | C108: =TEXT(Table1[[#This Row],[Order_Date]],"mmmm") -> August | D108: =YEAR(Table1[[#This Row],[Order_Date]]) -> 2025 | E108: 45891 | F108: =VLOOKUP(Table1[[#This Row],[Customer_ID]],Customer_Dim!$A$2:$H$501,2,FALSE) -> Tyrone Olson | G108: =_xlfn.XLOOKUP(Table1[[#This Row],[Customer_ID]],Customer_Dim!$A$2:$A$501,Customer_Dim!$E$2:$E$501) -> Emilytown | H108: CUST1269 | I108: =VLOOKUP(Table1[[#This Row],[Product_ID]],Product_Dim!$A$2:$G$101,2,FALSE) -> Knee Support Brace-Sports | J108: PROD19 | K108: =VLOOKUP(Table1[[#This Row],[Store_ID]],Store_Dim!$A$3:$D$22,2,FALSE) -> Guerrero-Schmitt-East | L108: STORE18 | M108: 3 | N108: 551.72 | O108: 0.03 | P108: COD | Q108: 1605.5052
A109: SALE107 | B109: ="Q" &ROUNDUP(MONTH(E109)/3,0) -> Q1 | C109: =TEXT(Table1[[#This Row],[Order_Date]],"mmmm") -> February | D109: =YEAR(Table1[[#This Row],[Order_Date]]) -> 2024 | E109: 45323 | F109: =VLOOKUP(Table1[[#This Row],[Customer_ID]],Customer_Dim!$A$2:$H$501,2,FALSE) -> Jasmine Snyder | G109: =_xlfn.XLOOKUP(Table1[[#This Row],[Customer_ID]],Customer_Dim!$A$2:$A$501,Customer_Dim!$E$2:$E$501) -> Hudsonfort | H109: CUST1338 | I109: =VLOOKUP(Table1[[#This Row],[Product_ID]],Product_Dim!$A$2:$G$101,2,FALSE) -> Kitchen Cutting Board-Home | J109: PROD86 | K109: =VLOOKUP(Table1[[#This Row],[Store_ID]],Store_Dim!$A$3:$D$22,2,FALSE) -> Martinez-Mullins-South | L109: STORE7 | M109: 4 | N109: 525.61 | O109: 0.02 | P109: PayPal | Q109: 2060.3912
... A197: SALE195 | B197: ="Q" &ROUNDUP(MONTH(E197)/3,0) -> Q4 | C197: =TEXT(Table1[[#This Row],[Order_Date]],"mmmm") -> December | D197: =YEAR(Table1[[#This Row],[Order_Date]]) -> 2023 | E197: 45290 | F197: =VLOOKUP(Table1[[#This Row],[Customer_ID]],Customer_Dim!$A$2:$H$501,2,FALSE) -> Jose Stewart | G197: =_xlfn.XLOOKUP(Table1[[#This Row],[Customer_ID]],Customer_Dim!$A$2:$A$501,Customer_Dim!$E$2:$E$501) -> South Robert | H197: CUST1427 | I197: =VLOOKUP(Table1[[#This Row],[Product_ID]],Product_Dim!$A$2:$G$101,2,FALSE) -> Luxury Perfume Spray-Beauty | J197: PROD60 | K197: =VLOOKUP(Table1[[#This Row],[Store_ID]],Store_Dim!$A$3:$D$22,2,FALSE) -> Holloway Ltd-North | L197: STORE17 | M197: 1 | N197: 889.19 | O197: 0.03 | P197: Credit Card | Q197: 862.5143
A198: SALE196 | B198: ="Q" &ROUNDUP(MONTH(E198)/3,0) -> Q3 | C198: =TEXT(Table1[[#This Row],[Order_Date]],"mmmm") -> September | D198: =YEAR(Table1[[#This Row],[Order_Date]]) -> 2025 | E198: 45904 | F198: Unknown | G198: Unknown | H198: CUST1464 | I198: =VLOOKUP(Table1[[#This Row],[Product_ID]],Product_Dim!$A$2:$G$101,2,FALSE) -> Foam Roller-Sports | J198: PROD57 | K198: =VLOOKUP(Table1[[#This Row],[Store_ID]],Store_Dim!$A$3:$D$22,2,FALSE) -> Frederick-Wright-West | L198: STORE16 | M198: 4 | N198: 689.67 | O198: 0.05 | P198: COD | Q198: 2620.746
A199: SALE197 | B199: ="Q" &ROUNDUP(MONTH(E199)/3,0) -> Q4 | C199: =TEXT(Table1[[#This Row],[Order_Date]],"mmmm") -> October | D199: =YEAR(Table1[[#This Row],[Order_Date]]) -> 2023 | E199: 45227 | F199: =VLOOKUP(Table1[[#This Row],[Customer_ID]],Customer_Dim!$A$2:$H$501,2,FALSE) -> Matthew Hanna | G199: =_xlfn.XLOOKUP(Table1[[#This Row],[Customer_ID]],Customer_Dim!$A$2:$A$501,Customer_Dim!$E$2:$E$501) -> Gonzalezbury | H199: CUST1135 | I199: =VLOOKUP(Table1[[#This Row],[Product_ID]],Product_Dim!$A$2:$G$101,2,FALSE) -> Adjustable Jump Rope-Sports | J199: PROD44 | K199: =VLOOKUP(Table1[[#This Row],[Store_ID]],Store_Dim!$A$3:$D$22,2,FALSE) -> Aguirre-Keller-South | L199: STORE11 | M199: 1 | N199: 541.24 | O199: 0.03 | P199: PayPal | Q199: 525.0028
A200: SALE198 | B200: ="Q" &ROUNDUP(MONTH(E200)/3,0) -> Q4 | C200: =TEXT(Table1[[#This Row],[Order_Date]],"mmmm") -> November | D200: =YEAR(Table1[[#This Row],[Order_Date]]) -> 2024 | E200: 45600 | F200: =VLOOKUP(Table1[[#This Row],[Customer_ID]],Customer_Dim!$A$2:$H$501,2,FALSE) -> Eric Holmes | G200: =_xlfn.XLOOKUP(Table1[[#This Row],[Customer_ID]],Customer_Dim!$A$2:$A$501,Customer_Dim!$E$2:$E$501) -> Smithville | H200: CUST1448 | I200: =VLOOKUP(Table1[[#This Row],[Product_ID]],Product_Dim!$A$2:$G$101,2,FALSE) -> Badminton Racket Set-Sports | J200: PROD81 | K200: =VLOOKUP(Table1[[#This Row],[Store_ID]],Store_Dim!$A$3:$D$22,2,FALSE) -> Benson-Elliott-East | L200: STORE6 | M200: 1 | N200: 454.71 | O200: 0.16 | P200: PayPal | Q200: 381.9564
A201: SALE199 | B201: ="Q" &ROUNDUP(MONTH(E201)/3,0) -> Q4 | C201: =TEXT(Table1[[#This Row],[Order_Date]],"mmmm") -> December | D201: =YEAR(Table1[[#This Row],[Order_Date]]) -> 2024 | E201: 45646 | F201: =VLOOKUP(Table1[[#This Row],[Customer_ID]],Customer_Dim!$A$2:$H$501,2,FALSE) -> Deanna Simpson | G201: =_xlfn.XLOOKUP(Table1[[#This Row],[Customer_ID]],Customer_Dim!$A$2:$A$501,Customer_Dim!$E$2:$E$501) -> Brownport | H201: CUST1038 | I201: =VLOOKUP(Table1[[#This Row],[Product_ID]],Product_Dim!$A$2:$G$101,2,FALSE) -> Women's Hair Dryer Brush-Beauty | J201: PROD66 | K201: =VLOOKUP(Table1[[#This Row],[Store_ID]],Store_Dim!$A$3:$D$22,2,FALSE) -> Gray Ltd-North | L201: STORE5 | M201: 2 | N201: 397.63 | O201: 0.26 | P201: Credit Card | Q201: 588.4924
A202: SALE200 | B202: ="Q" &ROUNDUP(MONTH(E202)/3,0) -> Q1 | C202: =TEXT(Table1[[#This Row],[Order_Date]],"mmmm") -> March | D202: =YEAR(Table1[[#This Row],[Order_Date]]) -> 2025 | E202: 45725 | F202: =VLOOKUP(Table1[[#This Row],[Customer_ID]],Customer_Dim!$A$2:$H$501,2,FALSE) -> Christopher Garcia Dds | G202: =_xlfn.XLOOKUP(Table1[[#This Row],[Customer_ID]],Customer_Dim!$A$2:$A$501,Customer_Dim!$E$2:$E$501) -> New Joseph | H202: CUST1170 | I202: =VLOOKUP(Table1[[#This Row],[Product_ID]],Product_Dim!$A$2:$G$101,2,FALSE) -> Hydrating Face Cleanser-Beauty | J202: PROD83 | K202: =VLOOKUP(Table1[[#This Row],[Store_ID]],Store_Dim!$A$3:$D$22,2,FALSE) -> Benson-Elliott-East | L202: STORE6 | M202: 3 | N202: 748.56 | O202: 0.26 | P202: PayPal | Q202: 1661.8032
A203: SALE201 | B203: ="Q" &ROUNDUP(MONTH(E203)/3,0) -> Q1 | C203: =TEXT(Table1[[#This Row],[Order_Date]],"mmmm") -> March | D203: =YEAR(Table1[[#This Row],[Order_Date]]) -> 2025 | E203: 45742 | F203: =VLOOKUP(Table1[[#This Row],[Customer_ID]],Customer_Dim!$A$2:$H$501,2,FALSE) -> Justin Cross | G203: =_xlfn.XLOOKUP(Table1[[#This Row],[Customer_ID]],Customer_Dim!$A$2:$A$501,Customer_Dim!$E$2:$E$501) -> North Anthonychester | H203: CUST1144 | I203: =VLOOKUP(Table1[[#This Row],[Product_ID]],Product_Dim!$A$2:$G$101,2,FALSE) -> Modern Wall Clock-Home | J203: PROD33 | K203: =VLOOKUP(Table1[[#This Row],[Store_ID]],Store_Dim!$A$3:$D$22,2,FALSE) -> Alexander Group-South | L203: STORE4 | M203: 1 | N203: 885.72 | O203: 0.15 | P203: Credit Card | Q203: 752.862
A204: SALE202 | B204: ="Q" &ROUNDUP(MONTH(E204)/3,0) -> Q2 | C204: =TEXT(Table1[[#This Row],[Order_Date]],"mmmm") -> April | D204: =YEAR(Table1[[#This Row],[Order_Date]]) -> 2025 | E204: 45750 | F204: =VLOOKUP(Table1[[#This Row],[Customer_ID]],Customer_Dim!$A$2:$H$501,2,FALSE) -> Travis Holland | G204: =_xlfn.XLOOKUP(Table1[[#This Row],[Customer_ID]],Customer_Dim!$A$2:$A$501,Customer_Dim!$E$2:$E$501) -> Webstermouth | H204: CUST1108 | I204: =VLOOKUP(Table1[[#This Row],[Product_ID]],Product_Dim!$A$2:$G$101,2,FALSE) -> Laptop Cooling Pad-Electronics | J204: PROD62 | K204: =VLOOKUP(Table1[[#This Row],[Store_ID]],Store_Dim!$A$3:$D$22,2,FALSE) -> Martinez, Adkins and Johnson-North | L204: STORE1 | M204: 4 | N204: 408.07 | O204: 0.28 | P204: COD | Q204: 1175.2416
A205: SALE203 | B205: ="Q" &ROUNDUP(MONTH(E205)/3,0) -> Q1 | C205: =TEXT(Table1[[#This Row],[Order_Date]],"mmmm") -> February | D205: =YEAR(Table1[[#This Row],[Order_Date]]) -> 2024 | E205: 45327 | F205: =VLOOKUP(Table1[[#This Row],[Customer_ID]],Customer_Dim!$A$2:$H$501,2,FALSE) -> Philip Mendoza | G205: =_xlfn.XLOOKUP(Table1[[#This Row],[Customer_ID]],Customer_Dim!$A$2:$A$501,Customer_Dim!$E$2:$E$501) -> Tylermouth | H205: CUST1472 | I205: =VLOOKUP(Table1[[#This Row],[Product_ID]],Product_Dim!$A$2:$G$101,2,FALSE) -> Gaming Mechanical Keyboard-Electronics | J205: PROD34 | K205: =VLOOKUP(Table1[[#This Row],[Store_ID]],Store_Dim!$A$3:$D$22,2,FALSE) -> Moore, Padilla and Butler-South | L205: STORE9 | M205: 2 | N205: 597.07 | O205: 0.28 | P205: PayPal | Q205: 859.7808
A206: SALE204 | B206: ="Q" &ROUNDUP(MONTH(E206)/3,0) -> Q2 | C206: =TEXT(Table1[[#This Row],[Order_Date]],"mmmm") -> June | D206: =YEAR(Table1[[#This Row],[Order_Date]]) -> 2024 | E206: 45465 | F206: =VLOOKUP(Table1[[#This Row],[Customer_ID]],Customer_Dim!$A$2:$H$501,2,FALSE) -> Paul Fox | G206: =_xlfn.XLOOKUP(Table1[[#This Row],[Customer_ID]],Customer_Dim!$A$2:$A$501,Customer_Dim!$E$2:$E$501) -> Michaelton | H206: CUST1022 | I206: =VLOOKUP(Table1[[#This Row],[Product_ID]],Product_Dim!$A$2:$G$101,2,FALSE) -> Smart LED Light Strip-Electronics | J206: PROD67 | K206: =VLOOKUP(Table1[[#This Row],[Store_ID]],Store_Dim!$A$3:$D$22,2,FALSE) -> Moore, Padilla and Butler-South | L206: STORE9 | M206: 3 | N206: 723.47 | O206: 0.12 | P206: COD | Q206: 1909.9608
A207: SALE205 | B207: ="Q" &ROUNDUP(MONTH(E207)/3,0) -> Q3 | C207: =TEXT(Table1[[#This Row],[Order_Date]],"mmmm") -> August | D207: =YEAR(Table1[[#This Row],[Order_Date]]) -> 2025 | E207: 45883 | F207: =VLOOKUP(Table1[[#This Row],[Customer_ID]],Customer_Dim!$A$2:$H$501,2,FALSE) -> Melinda Rivera | G207: =_xlfn.XLOOKUP(Table1[[#This Row],[Customer_ID]],Customer_Dim!$A$2:$A$501,Customer_Dim!$E$2:$E$501) -> East Davidmouth | H207: CUST1437 | I207: =VLOOKUP(Table1[[#This Row],[Product_ID]],Product_Dim!$A$2:$G$101,2,FALSE) -> Sports Wrist Sweatbands-Sports | J207: PROD88 | K207: =VLOOKUP(Table1[[#This Row],[Store_ID]],Store_Dim!$A$3:$D$22,2,FALSE) -> Gray Ltd-North | L207: STORE5 | M207: 1 | N207: 479.93 | O207: 0.22 | P207: Credit Card | Q207: 374.3454
A208: SALE206 | B208: ="Q" &ROUNDUP(MONTH(E208)/3,0) -> Q2 | C208: =TEXT(Table1[[#This Row],[Order_Date]],"mmmm") -> June | D208: =YEAR(Table1[[#This Row],[Order_Date]]) -> 2024 | E208: 45445 | F208: =VLOOKUP(Table1[[#This Row],[Customer_ID]],Customer_Dim!$A$2:$H$501,2,FALSE) -> Brian Hammond | G208: =_xlfn.XLOOKUP(Table1[[#This Row],[Customer_ID]],Customer_Dim!$A$2:$A$501,Customer_Dim!$E$2:$E$501) -> North Nicholas | H208: CUST1243 | I208: =VLOOKUP(Table1[[#This Row],[Product_ID]],Product_Dim!$A$2:$G$101,2,FALSE) -> Gaming Mechanical Keyboard-Electronics | J208: PROD34 | K208: =VLOOKUP(Table1[[#This Row],[Store_ID]],Store_Dim!$A$3:$D$22,2,FALSE) -> Frederick-Wright-West | L208: STORE16 | M208: 4 | N208: 362.81 | O208: 0.21 | P208: COD | Q208: 1146.4796
A209: SALE207 | B209: ="Q" &ROUNDUP(MONTH(E209)/3,0) -> Q4 | C209: =TEXT(Table1[[#This Row],[Order_Date]],"mmmm") -> December | D209: =YEAR(Table1[[#This Row],[Order_Date]]) -> 2024 | E209: 45640 | F209: =VLOOKUP(Table1[[#This Row],[Customer_ID]],Customer_Dim!$A$2:$H$501,2,FALSE) -> Brent Rivas | G209: =_xlfn.XLOOKUP(Table1[[#This Row],[Customer_ID]],Customer_Dim!$A$2:$A$501,Customer_Dim!$E$2:$E$501) -> North Kellyberg | H209: CUST1185 | I209: =VLOOKUP(Table1[[#This Row],[Product_ID]],Product_Dim!$A$2:$G$101,2,FALSE) -> Decorative Lamp Shade-Home | J209: PROD79 | K209: =VLOOKUP(Table1[[#This Row],[Store_ID]],Store_Dim!$A$3:$D$22,2,FALSE) -> Johnson-Wright-North | L209: STORE3 | M209: 1 | N209: 127.11 | O209: 0.01 | P209: PayPal | Q209: 125.8389
A210: SALE208 | B210: ="Q" &ROUNDUP(MONTH(E210)/3,0) -> Q2 | C210: =TEXT(Table1[[#This Row],[Order_Date]],"mmmm") -> April | D210: =YEAR(Table1[[#This Row],[Order_Date]]) -> 2024 | E210: 45411 | F210: =VLOOKUP(Table1[[#This Row],[Customer_ID]],Customer_Dim!$A$2:$H$501,2,FALSE) -> Leonard Cochran | G210: =_xlfn.XLOOKUP(Table1[[#This Row],[Customer_ID]],Customer_Dim!$A$2:$A$501,Customer_Dim!$E$2:$E$501) -> Port Sherryview | H210: CUST1184 | I210: =VLOOKUP(Table1[[#This Row],[Product_ID]],Product_Dim!$A$2:$G$101,2,FALSE) -> Gaming Mechanical Keyboard-Electronics | J210: PROD34 | K210: =VLOOKUP(Table1[[#This Row],[Store_ID]],Store_Dim!$A$3:$D$22,2,FALSE) -> Holloway Ltd-North | L210: STORE17 | M210: 4 | N210: 931.26 | O210: 0.04 | P210: Credit Card | Q210: 3576.0384
... A1021: SALE1019 | B1021: ="Q" &ROUNDUP(MONTH(E1021)/3,0) -> Q1 | C1021: =TEXT(Table1[[#This Row],[Order_Date]],"mmmm") -> March | D1021: =YEAR(Table1[[#This Row],[Order_Date]]) -> 2025 | E1021: 45733 | F1021: =VLOOKUP(Table1[[#This Row],[Customer_ID]],Customer_Dim!$A$2:$H$501,2,FALSE) -> Laura Green | G1021: =_xlfn.XLOOKUP(Table1[[#This Row],[Customer_ID]],Customer_Dim!$A$2:$A$501,Customer_Dim!$E$2:$E$501) -> Westbury | H1021: CUST1353 | I1021: =VLOOKUP(Table1[[#This Row],[Product_ID]],Product_Dim!$A$2:$G$101,2,FALSE) -> High-Grip Football-Sports | J1021: PROD45 | K1021: =VLOOKUP(Table1[[#This Row],[Store_ID]],Store_Dim!$A$3:$D$22,2,FALSE) -> Alexander Group-South | L1021: STORE4 | M1021: 2 | N1021: 825.04 | O1021: 0.2 | P1021: Credit Card | Q1021: 1320.064
A1022: SALE1020 | B1022: ="Q" &ROUNDUP(MONTH(E1022)/3,0) -> Q1 | C1022: =TEXT(Table1[[#This Row],[Order_Date]],"mmmm") -> January | D1022: =YEAR(Table1[[#This Row],[Order_Date]]) -> 2024 | E1022: 45322 | F1022: Unknown | G1022: Unknown | H1022: CUST1464 | I1022: =VLOOKUP(Table1[[#This Row],[Product_ID]],Product_Dim!$A$2:$G$101,2,FALSE) -> Women's Scarf Set-Clothing | J1022: PROD25 | K1022: =VLOOKUP(Table1[[#This Row],[Store_ID]],Store_Dim!$A$3:$D$22,2,FALSE) -> Gardner, Humphrey and Contreras-East | L1022: STORE13 | M1022: 1 | N1022: 963.76 | O1022: 0.14 | P1022: PayPal | Q1022: 828.8336
A1023: SALE1021 | B1023: ="Q" &ROUNDUP(MONTH(E1023)/3,0) -> Q2 | C1023: =TEXT(Table1[[#This Row],[Order_Date]],"mmmm") -> May | D1023: =YEAR(Table1[[#This Row],[Order_Date]]) -> 2024 | E1023: 45415 | F1023: =VLOOKUP(Table1[[#This Row],[Customer_ID]],Customer_Dim!$A$2:$H$501,2,FALSE) -> Ricardo Jones | G1023: =_xlfn.XLOOKUP(Table1[[#This Row],[Customer_ID]],Customer_Dim!$A$2:$A$501,Customer_Dim!$E$2:$E$501) -> Danielland | H1023: CUST1292 | I1023: =VLOOKUP(Table1[[#This Row],[Product_ID]],Product_Dim!$A$2:$G$101,2,FALSE) -> Ceramic Plant Pot-Home | J1023: PROD55 | K1023: =VLOOKUP(Table1[[#This Row],[Store_ID]],Store_Dim!$A$3:$D$22,2,FALSE) -> Benson-Elliott-East | L1023: STORE6 | M1023: 1 | N1023: 238.24 | O1023: 0.12 | P1023: PayPal | Q1023: 209.6512
A1024: SALE1022 | B1024: ="Q" &ROUNDUP(MONTH(E1024)/3,0) -> Q4 | C1024: =TEXT(Table1[[#This Row],[Order_Date]],"mmmm") -> December | D1024: =YEAR(Table1[[#This Row],[Order_Date]]) -> 2024 | E1024: 45644 | F1024: =VLOOKUP(Table1[[#This Row],[Customer_ID]],Customer_Dim!$A$2:$H$501,2,FALSE) -> Christina Robertson | G1024: =_xlfn.XLOOKUP(Table1[[#This Row],[Customer_ID]],Customer_Dim!$A$2:$A$501,Customer_Dim!$E$2:$E$501) -> Hubbardborough | H1024: CUST1457 | I1024: =VLOOKUP(Table1[[#This Row],[Product_ID]],Product_Dim!$A$2:$G$101,2,FALSE) -> Fitness Resistance Bands-Sports | J1024: PROD82 | K1024: =VLOOKUP(Table1[[#This Row],[Store_ID]],Store_Dim!$A$3:$D$22,2,FALSE) -> Frederick-Wright-West | L1024: STORE16 | M1024: 1 | N1024: 756.63 | O1024: 0.04 | P1024: PayPal | Q1024: 726.3648
A1025: SALE1023 | B1025: ="Q" &ROUNDUP(MONTH(E1025)/3,0) -> Q3 | C1025: =TEXT(Table1[[#This Row],[Order_Date]],"mmmm") -> July | D1025: =YEAR(Table1[[#This Row],[Order_Date]]) -> 2025 | E1025: 45845 | F1025: =VLOOKUP(Table1[[#This Row],[Customer_ID]],Customer_Dim!$A$2:$H$501,2,FALSE) -> Michael Torres | G1025: =_xlfn.XLOOKUP(Table1[[#This Row],[Customer_ID]],Customer_Dim!$A$2:$A$501,Customer_Dim!$E$2:$E$501) -> Gonzalezfort | H1025: CUST1019 | I1025: =VLOOKUP(Table1[[#This Row],[Product_ID]],Product_Dim!$A$2:$G$101,2,FALSE) -> USB-C Laptop Charger-Electronics | J1025: PROD93 | K1025: =VLOOKUP(Table1[[#This Row],[Store_ID]],Store_Dim!$A$3:$D$22,2,FALSE) -> Martinez-Mullins-South | L1025: STORE7 | M1025: 3 | N1025: 159.76 | O1025: 0.22 | P1025: Credit Card | Q1025: 373.8384
A1026: SALE1024 | B1026: ="Q" &ROUNDUP(MONTH(E1026)/3,0) -> Q1 | C1026: =TEXT(Table1[[#This Row],[Order_Date]],"mmmm") -> March | D1026: =YEAR(Table1[[#This Row],[Order_Date]]) -> 2024 | E1026: 45354 | F1026: =VLOOKUP(Table1[[#This Row],[Customer_ID]],Customer_Dim!$A$2:$H$501,2,FALSE) -> Miranda King | G1026: =_xlfn.XLOOKUP(Table1[[#This Row],[Customer_ID]],Customer_Dim!$A$2:$A$501,Customer_Dim!$E$2:$E$501) -> West Mathew | H1026: CUST1368 | I1026: =VLOOKUP(Table1[[#This Row],[Product_ID]],Product_Dim!$A$2:$G$101,2,FALSE) -> Sports Stopwatch Basic-Sports | J1026: PROD95 | K1026: =VLOOKUP(Table1[[#This Row],[Store_ID]],Store_Dim!$A$3:$D$22,2,FALSE) -> Bean, Jones and Park-West | L1026: STORE8 | M1026: 1 | N1026: 329.94 | O1026: 0.14 | P1026: COD | Q1026: 283.7484
A1027: SALE1025 | B1027: ="Q" &ROUNDUP(MONTH(E1027)/3,0) -> Q1 | C1027: =TEXT(Table1[[#This Row],[Order_Date]],"mmmm") -> March | D1027: =YEAR(Table1[[#This Row],[Order_Date]]) -> 2025 | E1027: 45720 | F1027: =VLOOKUP(Table1[[#This Row],[Customer_ID]],Customer_Dim!$A$2:$H$501,2,FALSE) -> Dr. David Smith | G1027: =_xlfn.XLOOKUP(Table1[[#This Row],[Customer_ID]],Customer_Dim!$A$2:$A$501,Customer_Dim!$E$2:$E$501) -> Schmidtchester | H1027: CUST1060 | I1027: =VLOOKUP(Table1[[#This Row],[Product_ID]],Product_Dim!$A$2:$G$101,2,FALSE) -> Soccer Training Cone Set-Sports | J1027: PROD17 | K1027: =VLOOKUP(Table1[[#This Row],[Store_ID]],Store_Dim!$A$3:$D$22,2,FALSE) -> Bean, Jones and Park-West | L1027: STORE8 | M1027: 1 | N1027: 234.06 | O1027: 0.11 | P1027: PayPal | Q1027: 208.3134
A1028: SALE1026 | B1028: ="Q" &ROUNDUP(MONTH(E1028)/3,0) -> Q4 | C1028: =TEXT(Table1[[#This Row],[Order_Date]],"mmmm") -> December | D1028: =YEAR(Table1[[#This Row],[Order_Date]]) -> 2023 | E1028: 45278 | F1028: =VLOOKUP(Table1[[#This Row],[Customer_ID]],Customer_Dim!$A$2:$H$501,2,FALSE) -> Tiffany Williams | G1028: =_xlfn.XLOOKUP(Table1[[#This Row],[Customer_ID]],Customer_Dim!$A$2:$A$501,Customer_Dim!$E$2:$E$501) -> Richardsport | H1028: CUST1317 | I1028: =VLOOKUP(Table1[[#This Row],[Product_ID]],Product_Dim!$A$2:$G$101,2,FALSE) -> Badminton Racket Set-Sports | J1028: PROD81 | K1028: =VLOOKUP(Table1[[#This Row],[Store_ID]],Store_Dim!$A$3:$D$22,2,FALSE) -> Rivera-Warner-East | L1028: STORE0 | M1028: 2 | N1028: 773.75 | O1028: 0.16 | P1028: PayPal | Q1028: 1299.9
A1029: SALE1027 | B1029: ="Q" &ROUNDUP(MONTH(E1029)/3,0) -> Q2 | C1029: =TEXT(Table1[[#This Row],[Order_Date]],"mmmm") -> May | D1029: =YEAR(Table1[[#This Row],[Order_Date]]) -> 2024 | E1029: 45422 | F1029: =VLOOKUP(Table1[[#This Row],[Customer_ID]],Customer_Dim!$A$2:$H$501,2,FALSE) -> Sharon Simpson | G1029: =_xlfn.XLOOKUP(Table1[[#This Row],[Customer_ID]],Customer_Dim!$A$2:$A$501,Customer_Dim!$E$2:$E$501) -> South Michellebury | H1029: CUST1436 | I1029: =VLOOKUP(Table1[[#This Row],[Product_ID]],Product_Dim!$A$2:$G$101,2,FALSE) -> Rugby Ball-Sports | J1029: PROD52 | K1029: =VLOOKUP(Table1[[#This Row],[Store_ID]],Store_Dim!$A$3:$D$22,2,FALSE) -> Guerrero-Schmitt-East | L1029: STORE18 | M1029: 1 | N1029: 73.88 | O1029: 0.04 | P1029: Credit Card | Q1029: 70.9248
A1030: SALE1028 | B1030: ="Q" &ROUNDUP(MONTH(E1030)/3,0) -> Q1 | C1030: =TEXT(Table1[[#This Row],[Order_Date]],"mmmm") -> February | D1030: =YEAR(Table1[[#This Row],[Order_Date]]) -> 2024 | E1030: 45337 | F1030: =VLOOKUP(Table1[[#This Row],[Customer_ID]],Customer_Dim!$A$2:$H$501,2,FALSE) -> Christine Vaughn | G1030: =_xlfn.XLOOKUP(Table1[[#This Row],[Customer_ID]],Customer_Dim!$A$2:$A$501,Customer_Dim!$E$2:$E$501) -> East Amandamouth | H1030: CUST1005 | I1030: =VLOOKUP(Table1[[#This Row],[Product_ID]],Product_Dim!$A$2:$G$101,2,FALSE) -> Kitchen Cutting Board-Home | J1030: PROD86 | K1030: =VLOOKUP(Table1[[#This Row],[Store_ID]],Store_Dim!$A$3:$D$22,2,FALSE) -> Guerrero-Schmitt-East | L1030: STORE18 | M1030: 1 | N1030: 859.3 | O1030: 0.16 | P1030: PayPal | Q1030: 721.812
A1031: SALE1029 | B1031: ="Q" &ROUNDUP(MONTH(E1031)/3,0) -> Q3 | C1031: =TEXT(Table1[[#This Row],[Order_Date]],"mmmm") -> September | D1031: =YEAR(Table1[[#This Row],[Order_Date]]) -> 2024 | E1031: 45564 | F1031: =VLOOKUP(Table1[[#This Row],[Customer_ID]],Customer_Dim!$A$2:$H$501,2,FALSE) -> Jessica Mitchell | G1031: =_xlfn.XLOOKUP(Table1[[#This Row],[Customer_ID]],Customer_Dim!$A$2:$A$501,Customer_Dim!$E$2:$E$501) -> Matthewbury | H1031: CUST1129 | I1031: =VLOOKUP(Table1[[#This Row],[Product_ID]],Product_Dim!$A$2:$G$101,2,FALSE) -> Badminton Racket Set-Sports | J1031: PROD81 | K1031: =VLOOKUP(Table1[[#This Row],[Store_ID]],Store_Dim!$A$3:$D$22,2,FALSE) -> Benson-Elliott-East | L1031: STORE6 | M1031: 4 | N1031: 762.43 | O1031: 0.05 | P1031: Credit Card | Q1031: 2897.234
A1032: SALE1030 | B1032: ="Q" &ROUNDUP(MONTH(E1032)/3,0) -> Q2 | C1032: =TEXT(Table1[[#This Row],[Order_Date]],"mmmm") -> May | D1032: =YEAR(Table1[[#This Row],[Order_Date]]) -> 2024 | E1032: 45424 | F1032: =VLOOKUP(Table1[[#This Row],[Customer_ID]],Customer_Dim!$A$2:$H$501,2,FALSE) -> Donald Lee | G1032: =_xlfn.XLOOKUP(Table1[[#This Row],[Customer_ID]],Customer_Dim!$A$2:$A$501,Customer_Dim!$E$2:$E$501) -> Wongberg | H1032: CUST1124 | I1032: =VLOOKUP(Table1[[#This Row],[Product_ID]],Product_Dim!$A$2:$G$101,2,FALSE) -> Shin Guards – Adult-Sports | J1032: PROD73 | K1032: =VLOOKUP(Table1[[#This Row],[Store_ID]],Store_Dim!$A$3:$D$22,2,FALSE) -> Rivera-Warner-East | L1032: STORE0 | M1032: 1 | N1032: 328.51 | O1032: 0.2 | P1032: COD | Q1032: 262.808
A1033: SALE1031 | B1033: ="Q" &ROUNDUP(MONTH(E1033)/3,0) -> Q1 | C1033: =TEXT(Table1[[#This Row],[Order_Date]],"mmmm") -> March | D1033: =YEAR(Table1[[#This Row],[Order_Date]]) -> 2025 | E1033: 45719 | F1033: =VLOOKUP(Table1[[#This Row],[Customer_ID]],Customer_Dim!$A$2:$H$501,2,FALSE) -> Sarah Lane | G1033: =_xlfn.XLOOKUP(Table1[[#This Row],[Customer_ID]],Customer_Dim!$A$2:$A$501,Customer_Dim!$E$2:$E$501) -> Edwardborough | H1033: CUST1274 | I1033: =VLOOKUP(Table1[[#This Row],[Product_ID]],Product_Dim!$A$2:$G$101,2,FALSE) -> Adjustable Jump Rope-Sports | J1033: PROD44 | K1033: =VLOOKUP(Table1[[#This Row],[Store_ID]],Store_Dim!$A$3:$D$22,2,FALSE) -> Alexander Group-South | L1033: STORE4 | M1033: 1 | N1033: 34.51 | O1033: 0.04 | P1033: COD | Q1033: 33.1296
A1034: SALE1032 | B1034: ="Q" &ROUNDUP(MONTH(E1034)/3,0) -> Q4 | C1034: =TEXT(Table1[[#This Row],[Order_Date]],"mmmm") -> November | D1034: =YEAR(Table1[[#This Row],[Order_Date]]) -> 2023 | E1034: 45250 | F1034: =VLOOKUP(Table1[[#This Row],[Customer_ID]],Customer_Dim!$A$2:$H$501,2,FALSE) -> Lance Baker | G1034: =_xlfn.XLOOKUP(Table1[[#This Row],[Customer_ID]],Customer_Dim!$A$2:$A$501,Customer_Dim!$E$2:$E$501) -> Port Victoria | H1034: CUST1105 | I1034: =VLOOKUP(Table1[[#This Row],[Product_ID]],Product_Dim!$A$2:$G$101,2,FALSE) -> Knee Support Brace-Sports | J1034: PROD19 | K1034: =VLOOKUP(Table1[[#This Row],[Store_ID]],Store_Dim!$A$3:$D$22,2,FALSE) -> Aguirre-Keller-South | L1034: STORE11 | M1034: 3 | N1034: 663.73 | O1034: 0.06 | P1034: COD | Q1034: 1871.7186
... A1056: SALE1054 | B1056: ="Q" &ROUNDUP(MONTH(E1056)/3,0) -> Q3 | C1056: =TEXT(Table1[[#This Row],[Order_Date]],"mmmm") -> July | D1056: =YEAR(Table1[[#This Row],[Order_Date]]) -> 2025 | E1056: 45850 | F1056: =VLOOKUP(Table1[[#This Row],[Customer_ID]],Customer_Dim!$A$2:$H$501,2,FALSE) -> Melinda Rivera | G1056: =_xlfn.XLOOKUP(Table1[[#This Row],[Customer_ID]],Customer_Dim!$A$2:$A$501,Customer_Dim!$E$2:$E$501) -> East Davidmouth | H1056: CUST1437 | I1056: =VLOOKUP(Table1[[#This Row],[Product_ID]],Product_Dim!$A$2:$G$101,2,FALSE) -> Bedroom Table Lamp-Home | J1056: PROD35 | K1056: =VLOOKUP(Table1[[#This Row],[Store_ID]],Store_Dim!$A$3:$D$22,2,FALSE) -> Thomas, Bridges and Harris-North | L1056: STORE12 | M1056: 3 | N1056: 471.31 | O1056: 0 | P1056: PayPal | Q1056: 1413.93
A1057: SALE1055 | B1057: ="Q" &ROUNDUP(MONTH(E1057)/3,0) -> Q2 | C1057: =TEXT(Table1[[#This Row],[Order_Date]],"mmmm") -> May | D1057: =YEAR(Table1[[#This Row],[Order_Date]]) -> 2024 | E1057: 45441 | F1057: Unknown | G1057: Unknown | H1057: CUST1464 | I1057: =VLOOKUP(Table1[[#This Row],[Product_ID]],Product_Dim!$A$2:$G$101,2,FALSE) -> Wireless Mouse-Electronics | J1057: PROD76 | K1057: =VLOOKUP(Table1[[#This Row],[Store_ID]],Store_Dim!$A$3:$D$22,2,FALSE) -> Mcdonald Inc-South | L1057: STORE14 | M1057: 2 | N1057: 720.32 | O1057: 0.26 | P1057: Credit Card | Q1057: 1066.0736
A1058: SALE1056 | B1058: ="Q" &ROUNDUP(MONTH(E1058)/3,0) -> Q2 | C1058: =TEXT(Table1[[#This Row],[Order_Date]],"mmmm") -> May | D1058: =YEAR(Table1[[#This Row],[Order_Date]]) -> 2024 | E1058: 45431 | F1058: =VLOOKUP(Table1[[#This Row],[Customer_ID]],Customer_Dim!$A$2:$H$501,2,FALSE) -> Rhonda Morales | G1058: =_xlfn.XLOOKUP(Table1[[#This Row],[Customer_ID]],Customer_Dim!$A$2:$A$501,Customer_Dim!$E$2:$E$501) -> Lake Barryfurt | H1058: CUST1075 | I1058: =VLOOKUP(Table1[[#This Row],[Product_ID]],Product_Dim!$A$2:$G$101,2,FALSE) -> Women's Hair Dryer Brush-Beauty | J1058: PROD66 | K1058: =VLOOKUP(Table1[[#This Row],[Store_ID]],Store_Dim!$A$3:$D$22,2,FALSE) -> Guerrero-Schmitt-East | L1058: STORE18 | M1058: 4 | N1058: 99.92 | O1058: 0.11 | P1058: COD | Q1058: 355.7152
A1059: SALE1057 | B1059: ="Q" &ROUNDUP(MONTH(E1059)/3,0) -> Q3 | C1059: =TEXT(Table1[[#This Row],[Order_Date]],"mmmm") -> August | D1059: =YEAR(Table1[[#This Row],[Order_Date]]) -> 2025 | E1059: 45873 | F1059: =VLOOKUP(Table1[[#This Row],[Customer_ID]],Customer_Dim!$A$2:$H$501,2,FALSE) -> Amber Mcclain | G1059: =_xlfn.XLOOKUP(Table1[[#This Row],[Customer_ID]],Customer_Dim!$A$2:$A$501,Customer_Dim!$E$2:$E$501) -> Brendaburgh | H1059: CUST1067 | I1059: =VLOOKUP(Table1[[#This Row],[Product_ID]],Product_Dim!$A$2:$G$101,2,FALSE) -> Ceramic Kitchen Bowl Set-Home | J1059: PROD10 | K1059: =VLOOKUP(Table1[[#This Row],[Store_ID]],Store_Dim!$A$3:$D$22,2,FALSE) -> Johnson-Wright-North | L1059: STORE3 | M1059: 3 | N1059: 900.63 | O1059: 0.11 | P1059: COD | Q1059: 2404.6821
A1060: SALE1058 | B1060: ="Q" &ROUNDUP(MONTH(E1060)/3,0) -> Q4 | C1060: =TEXT(Table1[[#This Row],[Order_Date]],"mmmm") -> December | D1060: =YEAR(Table1[[#This Row],[Order_Date]]) -> 2024 | E1060: 45629 | F1060: =VLOOKUP(Table1[[#This Row],[Customer_ID]],Customer_Dim!$A$2:$H$501,2,FALSE) -> Kelli Smith | G1060: =_xlfn.XLOOKUP(Table1[[#This Row],[Customer_ID]],Customer_Dim!$A$2:$A$501,Customer_Dim!$E$2:$E$501) -> North Maryfort | H1060: CUST1442 | I1060: =VLOOKUP(Table1[[#This Row],[Product_ID]],Product_Dim!$A$2:$G$101,2,FALSE) -> Men's Winter Jacket-Clothing | J1060: PROD46 | K1060: =VLOOKUP(Table1[[#This Row],[Store_ID]],Store_Dim!$A$3:$D$22,2,FALSE) -> Bean, Jones and Park-West | L1060: STORE8 | M1060: 1 | N1060: 681.72 | O1060: 0.11 | P1060: PayPal | Q1060: 606.7308
A1061: SALE1059 | B1061: ="Q" &ROUNDUP(MONTH(E1061)/3,0) -> Q4 | C1061: =TEXT(Table1[[#This Row],[Order_Date]],"mmmm") -> October | D1061: =YEAR(Table1[[#This Row],[Order_Date]]) -> 2023 | E1061: 45222 | F1061: =VLOOKUP(Table1[[#This Row],[Customer_ID]],Customer_Dim!$A$2:$H$501,2,FALSE) -> Ms. Maria Leach | G1061: =_xlfn.XLOOKUP(Table1[[#This Row],[Customer_ID]],Customer_Dim!$A$2:$A$501,Customer_Dim!$E$2:$E$501) -> Melissashire | H1061: CUST1009 | I1061: =VLOOKUP(Table1[[#This Row],[Product_ID]],Product_Dim!$A$2:$G$101,2,FALSE) -> Essential Oil Diffuser-Home | J1061: PROD78 | K1061: =VLOOKUP(Table1[[#This Row],[Store_ID]],Store_Dim!$A$3:$D$22,2,FALSE) -> Gardner, Humphrey and Contreras-East | L1061: STORE13 | M1061: 2 | N1061: 838.22 | O1061: 0.3 | P1061: Credit Card | Q1061: 1173.508
A1062: SALE1060 | B1062: ="Q" &ROUNDUP(MONTH(E1062)/3,0) -> Q2 | C1062: =TEXT(Table1[[#This Row],[Order_Date]],"mmmm") -> May | D1062: =YEAR(Table1[[#This Row],[Order_Date]]) -> 2025 | E1062: 45797 | F1062: =VLOOKUP(Table1[[#This Row],[Customer_ID]],Customer_Dim!$A$2:$H$501,2,FALSE) -> Ashley Ferguson | G1062: =_xlfn.XLOOKUP(Table1[[#This Row],[Customer_ID]],Customer_Dim!$A$2:$A$501,Customer_Dim!$E$2:$E$501) -> Sarahmouth | H1062: CUST1194 | I1062: =VLOOKUP(Table1[[#This Row],[Product_ID]],Product_Dim!$A$2:$G$101,2,FALSE) -> LED Bedside Lamp-Home | J1062: PROD87 | K1062: =VLOOKUP(Table1[[#This Row],[Store_ID]],Store_Dim!$A$3:$D$22,2,FALSE) -> Thomas, Bridges and Harris-North | L1062: STORE12 | M1062: 2 | N1062: 816.22 | O1062: 0.27 | P1062: Credit Card | Q1062: 1191.6812
A1063: SALE1061 | B1063: ="Q" &ROUNDUP(MONTH(E1063)/3,0) -> Q3 | C1063: =TEXT(Table1[[#This Row],[Order_Date]],"mmmm") -> September | D1063: =YEAR(Table1[[#This Row],[Order_Date]]) -> 2024 | E1063: 45554 | F1063: =VLOOKUP(Table1[[#This Row],[Customer_ID]],Customer_Dim!$A$2:$H$501,2,FALSE) -> Shelley Ponce | G1063: =_xlfn.XLOOKUP(Table1[[#This Row],[Customer_ID]],Customer_Dim!$A$2:$A$501,Customer_Dim!$E$2:$E$501) -> South Cassandrachester | H1063: CUST1380 | I1063: =VLOOKUP(Table1[[#This Row],[Product_ID]],Product_Dim!$A$2:$G$101,2,FALSE) -> Tennis Ball 3-Pack-Sports | J1063: PROD61 | K1063: =VLOOKUP(Table1[[#This Row],[Store_ID]],Store_Dim!$A$3:$D$22,2,FALSE) -> Martinez-Mullins-South | L1063: STORE7 | M1063: 2 | N1063: 654.12 | O1063: 0.27 | P1063: PayPal | Q1063: 955.0152
A1064: SALE1062 | B1064: ="Q" &ROUNDUP(MONTH(E1064)/3,0) -> Q2 | C1064: =TEXT(Table1[[#This Row],[Order_Date]],"mmmm") -> April | D1064: =YEAR(Table1[[#This Row],[Order_Date]]) -> 2024 | E1064: 45385 | F1064: =VLOOKUP(Table1[[#This Row],[Customer_ID]],Customer_Dim!$A$2:$H$501,2,FALSE) -> Lance Baker | G1064: =_xlfn.XLOOKUP(Table1[[#This Row],[Customer_ID]],Customer_Dim!$A$2:$A$501,Customer_Dim!$E$2:$E$501) -> Port Victoria | H1064: CUST1105 | I1064: =VLOOKUP(Table1[[#This Row],[Product_ID]],Product_Dim!$A$2:$G$101,2,FALSE) -> Shin Guards – Adult-Sports | J1064: PROD73 | K1064: =VLOOKUP(Table1[[#This Row],[Store_ID]],Store_Dim!$A$3:$D$22,2,FALSE) -> Gardner, Humphrey and Contreras-East | L1064: STORE13 | M1064: 4 | N1064: 528.22 | O1064: 0.2 | P1064: PayPal | Q1064: 1690.304
A1065: SALE1063 | B1065: ="Q" &ROUNDUP(MONTH(E1065)/3,0) -> Q1 | C1065: =TEXT(Table1[[#This Row],[Order_Date]],"mmmm") -> February | D1065: =YEAR(Table1[[#This Row],[Order_Date]]) -> 2025 | E1065: 45704 | F1065: =VLOOKUP(Table1[[#This Row],[Customer_ID]],Customer_Dim!$A$2:$H$501,2,FALSE) -> Lisa Young | G1065: =_xlfn.XLOOKUP(Table1[[#This Row],[Customer_ID]],Customer_Dim!$A$2:$A$501,Customer_Dim!$E$2:$E$501) -> Maybury | H1065: CUST1221 | I1065: =VLOOKUP(Table1[[#This Row],[Product_ID]],Product_Dim!$A$2:$G$101,2,FALSE) -> Gaming Mechanical Keyboard-Electronics | J1065: PROD34 | K1065: =VLOOKUP(Table1[[#This Row],[Store_ID]],Store_Dim!$A$3:$D$22,2,FALSE) -> Martinez-Mullins-South | L1065: STORE7 | M1065: 4 | N1065: 36.72 | O1065: 0.07 | P1065: COD | Q1065: 136.5984
A1066: SALE1064 | B1066: ="Q" &ROUNDUP(MONTH(E1066)/3,0) -> Q3 | C1066: =TEXT(Table1[[#This Row],[Order_Date]],"mmmm") -> September | D1066: =YEAR(Table1[[#This Row],[Order_Date]]) -> 2024 | E1066: 45545 | F1066: =VLOOKUP(Table1[[#This Row],[Customer_ID]],Customer_Dim!$A$2:$H$501,2,FALSE) -> James Holloway Jr. | G1066: =_xlfn.XLOOKUP(Table1[[#This Row],[Customer_ID]],Customer_Dim!$A$2:$A$501,Customer_Dim!$E$2:$E$501) -> Millston | H1066: CUST1370 | I1066: =VLOOKUP(Table1[[#This Row],[Product_ID]],Product_Dim!$A$2:$G$101,2,FALSE) -> Essential Oil Diffuser-Home | J1066: PROD78 | K1066: =VLOOKUP(Table1[[#This Row],[Store_ID]],Store_Dim!$A$3:$D$22,2,FALSE) -> Mann-Austin-East | L1066: STORE19 | M1066: 2 | N1066: 705.97 | O1066: 0.1 | P1066: PayPal | Q1066: 1270.746
A1067: SALE1065 | B1067: ="Q" &ROUNDUP(MONTH(E1067)/3,0) -> Q1 | C1067: =TEXT(Table1[[#This Row],[Order_Date]],"mmmm") -> March | D1067: =YEAR(Table1[[#This Row],[Order_Date]]) -> 2025 | E1067: 45736 | F1067: =VLOOKUP(Table1[[#This Row],[Customer_ID]],Customer_Dim!$A$2:$H$501,2,FALSE) -> Jonathan Steele | G1067: =_xlfn.XLOOKUP(Table1[[#This Row],[Customer_ID]],Customer_Dim!$A$2:$A$501,Customer_Dim!$E$2:$E$501) -> Molinabury | H1067: CUST1023 | I1067: =VLOOKUP(Table1[[#This Row],[Product_ID]],Product_Dim!$A$2:$G$101,2,FALSE) -> Noise-Canceling Headphones-Electronics | J1067: PROD40 | K1067: =VLOOKUP(Table1[[#This Row],[Store_ID]],Store_Dim!$A$3:$D$22,2,FALSE) -> Martinez, Adkins and Johnson-North | L1067: STORE1 | M1067: 2 | N1067: 994.29 | O1067: 0.01 | P1067: PayPal | Q1067: 1968.6942
A1068: SALE1066 | B1068: ="Q" &ROUNDUP(MONTH(E1068)/3,0) -> Q4 | C1068: =TEXT(Table1[[#This Row],[Order_Date]],"mmmm") -> November | D1068: =YEAR(Table1[[#This Row],[Order_Date]]) -> 2024 | E1068: 45608 | F1068: =VLOOKUP(Table1[[#This Row],[Customer_ID]],Customer_Dim!$A$2:$H$501,2,FALSE) -> Holly Robinson | G1068: =_xlfn.XLOOKUP(Table1[[#This Row],[Customer_ID]],Customer_Dim!$A$2:$A$501,Customer_Dim!$E$2:$E$501) -> East Amy | H1068: CUST1421 | I1068: =VLOOKUP(Table1[[#This Row],[Product_ID]],Product_Dim!$A$2:$G$101,2,FALSE) -> Microwave Oven-Home | J1068: PROD92 | K1068: =VLOOKUP(Table1[[#This Row],[Store_ID]],Store_Dim!$A$3:$D$22,2,FALSE) -> Guerrero-Schmitt-East | L1068: STORE18 | M1068: 1 | N1068: 909.04 | O1068: 0.11 | P1068: Credit Card | Q1068: 809.0456
...
